{"config": {"font": "Circular Std", "mark": {"line": {"interpolate": "monotone"}}, "view": {"stroke": "transparent", "width": 400, "height": 300}, "range": {"category": ["#36B7B4", "#E6224B", "#F4C245", "#0063AF", "#00A767", "#179FDB", "#EB5C2E"], "diverging": ["#E6224B", "#E54753", "#C9C9C9", "#179FDB", "#122B39"], "heatmap": ["#C9C9C9", "#179FDB", "#0063AF", "#122B39"], "ordinal": ["#00A767", "#36B7B4", "#179FDB", "#0063AF", "#243B5A"]}, "axisX": {"domainColor": "#676A86", "domainOpacity": 0.5, "grid": false, "labelAngle": 0, "labelColor": "#676A86", "labelOpacity": 0.7, "orient": "bottom", "tickColor": "#676A86", "tickCount": 10, "tickOpacity": 0.5, "title": false, "titleAlign": "center", "titleAnchor": "middle", "titleColor": "#676A86", "titleFontSize": 12, "titleOpacity": 0.8, "titleY": -15}, "axisY": {"domainColor": "#676A86", "domainOpacity": 0.5, "gridColor": "#676A86", "gridDash": [1, 5], "gridOpacity": 0.5, "labelColor": "#676A86", "labelOpacity": 0.7, "labelPadding": 5, "tickColor": "#676A86", "tickCount": 8, "tickOpacity": 0.5, "ticks": false, "titleAlign": "left", "titleAngle": 0, "titleBaseline": "bottom", "titleColor": "#676A86", "titleFontSize": 12, "titleOpacity": 0.8, "titleX": 0, "titleY": -7}}, "layer": [{"mark": {"type": "line", "point": {"filled": false, "opacity": {"expr": "if(datum.highlight, 1, 0)"}}}, "encoding": {"color": {"field": "Country", "legend": null, "scale": {"domain": ["World", "United Kingdom", "United States", "Kenya", "Japan"], "range": ["#36B7B4", "#E6224B", "#F4C245", "#0063AF", "#00A767"]}, "type": "nominal"}, "stroke": {"field": "Country", "legend": null, "scale": {"domain": ["World", "United Kingdom", "United States", "Kenya", "Japan"], "range": ["#36B7B4", "#E6224B", "#F4C245", "#0063AF", "#00A767"]}, "type": "nominal"}, "x": {"field": "date", "timeUnit": "year", "title": "", "type": "temporal"}, "y": {"field": "value", "scale": {"domain": [0, 10]}, "title": "", "type": "quantitative"}}}, {"mark": {"type": "text", "align": "left", "baseline": "middle", "dx": 5, "dy": {"expr": "\n            {   'United States': -6,\n            }[datum.Country]\n        "}, "fontSize": 12, "fontWeight": "bold"}, "encoding": {"color": {"field": "Country", "scale": {"domain": ["World", "United Kingdom", "United States", "Kenya", "Japan"], "range": ["#36B7B4", "#E6224B", "#F4C245", "#0063AF", "#00A767"]}, "type": "nominal"}, "text": {"field": "Country", "type": "nominal"}, "x": {"field": "date", "timeUnit": "year", "type": "temporal"}, "y": {"field": "value", "type": "quantitative"}}, "transform": [{"filter": "datum.highlight"}]}], "data": {"name": "data-c04520c91aee708d7c70b78393d8bb01"}, "title": {"text": "Global Fertility Rates", "frame": "group", "anchor": "start", "subtitle": ["Total births per woman, 1960 - 2022", "Source: World Bank", ""], "subtitleColor": "#676A86", "fontSize": 22}, "$schema": "https://vega.github.io/schema/vega-lite/v5.20.1.json", "datasets": {"data-c04520c91aee708d7c70b78393d8bb01": [{"Year": 1960, "Country": "Japan", "value": 2.0, "date": "1960-01-01T00:00:00", "highlight": false}, {"Year": 1961, "Country": "Japan", "value": 1.96, "date": "1961-01-01T00:00:00", "highlight": false}, {"Year": 1962, "Country": "Japan", "value": 1.98, "date": "1962-01-01T00:00:00", "highlight": false}, {"Year": 1963, "Country": "Japan", "value": 2.0, "date": "1963-01-01T00:00:00", "highlight": false}, {"Year": 1964, "Country": "Japan", "value": 2.05, "date": "1964-01-01T00:00:00", "highlight": false}, {"Year": 1965, "Country": "Japan", "value": 2.14, "date": "1965-01-01T00:00:00", "highlight": false}, {"Year": 1966, "Country": "Japan", "value": 1.58, "date": "1966-01-01T00:00:00", "highlight": false}, {"Year": 1967, "Country": "Japan", "value": 2.23, "date": "1967-01-01T00:00:00", "highlight": false}, {"Year": 1968, "Country": "Japan", "value": 2.13, "date": "1968-01-01T00:00:00", "highlight": false}, {"Year": 1969, "Country": "Japan", "value": 2.13, "date": "1969-01-01T00:00:00", "highlight": false}, {"Year": 1970, "Country": "Japan", "value": 2.13, "date": "1970-01-01T00:00:00", "highlight": false}, {"Year": 1971, "Country": "Japan", "value": 2.16, "date": "1971-01-01T00:00:00", "highlight": false}, {"Year": 1972, "Country": "Japan", "value": 2.14, "date": "1972-01-01T00:00:00", "highlight": false}, {"Year": 1973, "Country": "Japan", "value": 2.14, "date": "1973-01-01T00:00:00", "highlight": false}, {"Year": 1974, "Country": "Japan", "value": 2.05, "date": "1974-01-01T00:00:00", "highlight": false}, {"Year": 1975, "Country": "Japan", "value": 1.91, "date": "1975-01-01T00:00:00", "highlight": false}, {"Year": 1976, "Country": "Japan", "value": 1.85, "date": "1976-01-01T00:00:00", "highlight": false}, {"Year": 1977, "Country": "Japan", "value": 1.8, "date": "1977-01-01T00:00:00", "highlight": false}, {"Year": 1978, "Country": "Japan", "value": 1.79, "date": "1978-01-01T00:00:00", "highlight": false}, {"Year": 1979, "Country": "Japan", "value": 1.77, "date": "1979-01-01T00:00:00", "highlight": false}, {"Year": 1980, "Country": "Japan", "value": 1.75, "date": "1980-01-01T00:00:00", "highlight": false}, {"Year": 1981, "Country": "Japan", "value": 1.74, "date": "1981-01-01T00:00:00", "highlight": false}, {"Year": 1982, "Country": "Japan", "value": 1.77, "date": "1982-01-01T00:00:00", "highlight": false}, {"Year": 1983, "Country": "Japan", "value": 1.8, "date": "1983-01-01T00:00:00", "highlight": false}, {"Year": 1984, "Country": "Japan", "value": 1.81, "date": "1984-01-01T00:00:00", "highlight": false}, {"Year": 1985, "Country": "Japan", "value": 1.76, "date": "1985-01-01T00:00:00", "highlight": false}, {"Year": 1986, "Country": "Japan", "value": 1.72, "date": "1986-01-01T00:00:00", "highlight": false}, {"Year": 1987, "Country": "Japan", "value": 1.69, "date": "1987-01-01T00:00:00", "highlight": false}, {"Year": 1988, "Country": "Japan", "value": 1.66, "date": "1988-01-01T00:00:00", "highlight": false}, {"Year": 1989, "Country": "Japan", "value": 1.57, "date": "1989-01-01T00:00:00", "highlight": false}, {"Year": 1990, "Country": "Japan", "value": 1.54, "date": "1990-01-01T00:00:00", "highlight": false}, {"Year": 1991, "Country": "Japan", "value": 1.53, "date": "1991-01-01T00:00:00", "highlight": false}, {"Year": 1992, "Country": "Japan", "value": 1.5, "date": "1992-01-01T00:00:00", "highlight": false}, {"Year": 1993, "Country": "Japan", "value": 1.46, "date": "1993-01-01T00:00:00", "highlight": false}, {"Year": 1994, "Country": "Japan", "value": 1.5, "date": "1994-01-01T00:00:00", "highlight": false}, {"Year": 1995, "Country": "Japan", "value": 1.42, "date": "1995-01-01T00:00:00", "highlight": false}, {"Year": 1996, "Country": "Japan", "value": 1.43, "date": "1996-01-01T00:00:00", "highlight": false}, {"Year": 1997, "Country": "Japan", "value": 1.39, "date": "1997-01-01T00:00:00", "highlight": false}, {"Year": 1998, "Country": "Japan", "value": 1.38, "date": "1998-01-01T00:00:00", "highlight": false}, {"Year": 1999, "Country": "Japan", "value": 1.34, "date": "1999-01-01T00:00:00", "highlight": false}, {"Year": 2000, "Country": "Japan", "value": 1.36, "date": "2000-01-01T00:00:00", "highlight": false}, {"Year": 2001, "Country": "Japan", "value": 1.33, "date": "2001-01-01T00:00:00", "highlight": false}, {"Year": 2002, "Country": "Japan", "value": 1.32, "date": "2002-01-01T00:00:00", "highlight": false}, {"Year": 2003, "Country": "Japan", "value": 1.29, "date": "2003-01-01T00:00:00", "highlight": false}, {"Year": 2004, "Country": "Japan", "value": 1.29, "date": "2004-01-01T00:00:00", "highlight": false}, {"Year": 2005, "Country": "Japan", "value": 1.26, "date": "2005-01-01T00:00:00", "highlight": false}, {"Year": 2006, "Country": "Japan", "value": 1.32, "date": "2006-01-01T00:00:00", "highlight": false}, {"Year": 2007, "Country": "Japan", "value": 1.34, "date": "2007-01-01T00:00:00", "highlight": false}, {"Year": 2008, "Country": "Japan", "value": 1.37, "date": "2008-01-01T00:00:00", "highlight": false}, {"Year": 2009, "Country": "Japan", "value": 1.37, "date": "2009-01-01T00:00:00", "highlight": false}, {"Year": 2010, "Country": "Japan", "value": 1.39, "date": "2010-01-01T00:00:00", "highlight": false}, {"Year": 2011, "Country": "Japan", "value": 1.39, "date": "2011-01-01T00:00:00", "highlight": false}, {"Year": 2012, "Country": "Japan", "value": 1.41, "date": "2012-01-01T00:00:00", "highlight": false}, {"Year": 2013, "Country": "Japan", "value": 1.43, "date": "2013-01-01T00:00:00", "highlight": false}, {"Year": 2014, "Country": "Japan", "value": 1.42, "date": "2014-01-01T00:00:00", "highlight": false}, {"Year": 2015, "Country": "Japan", "value": 1.45, "date": "2015-01-01T00:00:00", "highlight": false}, {"Year": 2016, "Country": "Japan", "value": 1.44, "date": "2016-01-01T00:00:00", "highlight": false}, {"Year": 2017, "Country": "Japan", "value": 1.43, "date": "2017-01-01T00:00:00", "highlight": false}, {"Year": 2018, "Country": "Japan", "value": 1.42, "date": "2018-01-01T00:00:00", "highlight": false}, {"Year": 2019, "Country": "Japan", "value": 1.36, "date": "2019-01-01T00:00:00", "highlight": false}, {"Year": 2020, "Country": "Japan", "value": 1.33, "date": "2020-01-01T00:00:00", "highlight": false}, {"Year": 2021, "Country": "Japan", "value": 1.3, "date": "2021-01-01T00:00:00", "highlight": false}, {"Year": 2022, "Country": "Japan", "value": 1.26, "date": "2022-01-01T00:00:00", "highlight": true}, {"Year": 1960, "Country": "Kenya", "value": 7.632, "date": "1960-01-01T00:00:00", "highlight": false}, {"Year": 1961, "Country": "Kenya", "value": 7.718, "date": "1961-01-01T00:00:00", "highlight": false}, {"Year": 1962, "Country": "Kenya", "value": 7.803, "date": "1962-01-01T00:00:00", "highlight": false}, {"Year": 1963, "Country": "Kenya", "value": 7.864, "date": "1963-01-01T00:00:00", "highlight": false}, {"Year": 1964, "Country": "Kenya", "value": 7.92, "date": "1964-01-01T00:00:00", "highlight": false}, {"Year": 1965, "Country": "Kenya", "value": 8.028, "date": "1965-01-01T00:00:00", "highlight": false}, {"Year": 1966, "Country": "Kenya", "value": 8.056, "date": "1966-01-01T00:00:00", "highlight": false}, {"Year": 1967, "Country": "Kenya", "value": 8.046, "date": "1967-01-01T00:00:00", "highlight": false}, {"Year": 1968, "Country": "Kenya", "value": 8.038, "date": "1968-01-01T00:00:00", "highlight": false}, {"Year": 1969, "Country": "Kenya", "value": 8.031, "date": "1969-01-01T00:00:00", "highlight": false}, {"Year": 1970, "Country": "Kenya", "value": 8.024, "date": "1970-01-01T00:00:00", "highlight": false}, {"Year": 1971, "Country": "Kenya", "value": 8.003, "date": "1971-01-01T00:00:00", "highlight": false}, {"Year": 1972, "Country": "Kenya", "value": 7.975, "date": "1972-01-01T00:00:00", "highlight": false}, {"Year": 1973, "Country": "Kenya", "value": 7.939, "date": "1973-01-01T00:00:00", "highlight": false}, {"Year": 1974, "Country": "Kenya", "value": 7.907, "date": "1974-01-01T00:00:00", "highlight": false}, {"Year": 1975, "Country": "Kenya", "value": 7.877, "date": "1975-01-01T00:00:00", "highlight": false}, {"Year": 1976, "Country": "Kenya", "value": 7.843, "date": "1976-01-01T00:00:00", "highlight": false}, {"Year": 1977, "Country": "Kenya", "value": 7.803, "date": "1977-01-01T00:00:00", "highlight": false}, {"Year": 1978, "Country": "Kenya", "value": 7.746, "date": "1978-01-01T00:00:00", "highlight": false}, {"Year": 1979, "Country": "Kenya", "value": 7.679, "date": "1979-01-01T00:00:00", "highlight": false}, {"Year": 1980, "Country": "Kenya", "value": 7.598, "date": "1980-01-01T00:00:00", "highlight": false}, {"Year": 1981, "Country": "Kenya", "value": 7.513, "date": "1981-01-01T00:00:00", "highlight": false}, {"Year": 1982, "Country": "Kenya", "value": 7.402, "date": "1982-01-01T00:00:00", "highlight": false}, {"Year": 1983, "Country": "Kenya", "value": 7.263, "date": "1983-01-01T00:00:00", "highlight": false}, {"Year": 1984, "Country": "Kenya", "value": 7.123, "date": "1984-01-01T00:00:00", "highlight": false}, {"Year": 1985, "Country": "Kenya", "value": 6.975, "date": "1985-01-01T00:00:00", "highlight": false}, {"Year": 1986, "Country": "Kenya", "value": 6.848, "date": "1986-01-01T00:00:00", "highlight": false}, {"Year": 1987, "Country": "Kenya", "value": 6.682, "date": "1987-01-01T00:00:00", "highlight": false}, {"Year": 1988, "Country": "Kenya", "value": 6.505, "date": "1988-01-01T00:00:00", "highlight": false}, {"Year": 1989, "Country": "Kenya", "value": 6.323, "date": "1989-01-01T00:00:00", "highlight": false}, {"Year": 1990, "Country": "Kenya", "value": 6.129, "date": "1990-01-01T00:00:00", "highlight": false}, {"Year": 1991, "Country": "Kenya", "value": 5.935, "date": "1991-01-01T00:00:00", "highlight": false}, {"Year": 1992, "Country": "Kenya", "value": 5.746, "date": "1992-01-01T00:00:00", "highlight": false}, {"Year": 1993, "Country": "Kenya", "value": 5.574, "date": "1993-01-01T00:00:00", "highlight": false}, {"Year": 1994, "Country": "Kenya", "value": 5.446, "date": "1994-01-01T00:00:00", "highlight": false}, {"Year": 1995, "Country": "Kenya", "value": 5.366, "date": "1995-01-01T00:00:00", "highlight": false}, {"Year": 1996, "Country": "Kenya", "value": 5.306, "date": "1996-01-01T00:00:00", "highlight": false}, {"Year": 1997, "Country": "Kenya", "value": 5.26, "date": "1997-01-01T00:00:00", "highlight": false}, {"Year": 1998, "Country": "Kenya", "value": 5.246, "date": "1998-01-01T00:00:00", "highlight": false}, {"Year": 1999, "Country": "Kenya", "value": 5.181, "date": "1999-01-01T00:00:00", "highlight": false}, {"Year": 2000, "Country": "Kenya", "value": 5.137, "date": "2000-01-01T00:00:00", "highlight": false}, {"Year": 2001, "Country": "Kenya", "value": 5.091, "date": "2001-01-01T00:00:00", "highlight": false}, {"Year": 2002, "Country": "Kenya", "value": 5.016, "date": "2002-01-01T00:00:00", "highlight": false}, {"Year": 2003, "Country": "Kenya", "value": 4.907, "date": "2003-01-01T00:00:00", "highlight": false}, {"Year": 2004, "Country": "Kenya", "value": 4.83, "date": "2004-01-01T00:00:00", "highlight": false}, {"Year": 2005, "Country": "Kenya", "value": 4.784, "date": "2005-01-01T00:00:00", "highlight": false}, {"Year": 2006, "Country": "Kenya", "value": 4.748, "date": "2006-01-01T00:00:00", "highlight": false}, {"Year": 2007, "Country": "Kenya", "value": 4.719, "date": "2007-01-01T00:00:00", "highlight": false}, {"Year": 2008, "Country": "Kenya", "value": 4.646, "date": "2008-01-01T00:00:00", "highlight": false}, {"Year": 2009, "Country": "Kenya", "value": 4.514, "date": "2009-01-01T00:00:00", "highlight": false}, {"Year": 2010, "Country": "Kenya", "value": 4.367, "date": "2010-01-01T00:00:00", "highlight": false}, {"Year": 2011, "Country": "Kenya", "value": 4.219, "date": "2011-01-01T00:00:00", "highlight": false}, {"Year": 2012, "Country": "Kenya", "value": 4.088, "date": "2012-01-01T00:00:00", "highlight": false}, {"Year": 2013, "Country": "Kenya", "value": 3.952, "date": "2013-01-01T00:00:00", "highlight": false}, {"Year": 2014, "Country": "Kenya", "value": 3.844, "date": "2014-01-01T00:00:00", "highlight": false}, {"Year": 2015, "Country": "Kenya", "value": 3.8, "date": "2015-01-01T00:00:00", "highlight": false}, {"Year": 2016, "Country": "Kenya", "value": 3.724, "date": "2016-01-01T00:00:00", "highlight": false}, {"Year": 2017, "Country": "Kenya", "value": 3.643, "date": "2017-01-01T00:00:00", "highlight": false}, {"Year": 2018, "Country": "Kenya", "value": 3.58, "date": "2018-01-01T00:00:00", "highlight": false}, {"Year": 2019, "Country": "Kenya", "value": 3.469, "date": "2019-01-01T00:00:00", "highlight": false}, {"Year": 2020, "Country": "Kenya", "value": 3.397, "date": "2020-01-01T00:00:00", "highlight": false}, {"Year": 2021, "Country": "Kenya", "value": 3.335, "date": "2021-01-01T00:00:00", "highlight": false}, {"Year": 2022, "Country": "Kenya", "value": 3.296, "date": "2022-01-01T00:00:00", "highlight": true}, {"Year": 1960, "Country": "United Kingdom", "value": 2.69, "date": "1960-01-01T00:00:00", "highlight": false}, {"Year": 1961, "Country": "United Kingdom", "value": 2.78, "date": "1961-01-01T00:00:00", "highlight": false}, {"Year": 1962, "Country": "United Kingdom", "value": 2.86, "date": "1962-01-01T00:00:00", "highlight": false}, {"Year": 1963, "Country": "United Kingdom", "value": 2.88, "date": "1963-01-01T00:00:00", "highlight": false}, {"Year": 1964, "Country": "United Kingdom", "value": 2.93, "date": "1964-01-01T00:00:00", "highlight": false}, {"Year": 1965, "Country": "United Kingdom", "value": 2.86, "date": "1965-01-01T00:00:00", "highlight": false}, {"Year": 1966, "Country": "United Kingdom", "value": 2.78, "date": "1966-01-01T00:00:00", "highlight": false}, {"Year": 1967, "Country": "United Kingdom", "value": 2.68, "date": "1967-01-01T00:00:00", "highlight": false}, {"Year": 1968, "Country": "United Kingdom", "value": 2.6, "date": "1968-01-01T00:00:00", "highlight": false}, {"Year": 1969, "Country": "United Kingdom", "value": 2.51, "date": "1969-01-01T00:00:00", "highlight": false}, {"Year": 1970, "Country": "United Kingdom", "value": 2.44, "date": "1970-01-01T00:00:00", "highlight": false}, {"Year": 1971, "Country": "United Kingdom", "value": 2.41, "date": "1971-01-01T00:00:00", "highlight": false}, {"Year": 1972, "Country": "United Kingdom", "value": 2.2, "date": "1972-01-01T00:00:00", "highlight": false}, {"Year": 1973, "Country": "United Kingdom", "value": 2.04, "date": "1973-01-01T00:00:00", "highlight": false}, {"Year": 1974, "Country": "United Kingdom", "value": 1.92, "date": "1974-01-01T00:00:00", "highlight": false}, {"Year": 1975, "Country": "United Kingdom", "value": 1.81, "date": "1975-01-01T00:00:00", "highlight": false}, {"Year": 1976, "Country": "United Kingdom", "value": 1.74, "date": "1976-01-01T00:00:00", "highlight": false}, {"Year": 1977, "Country": "United Kingdom", "value": 1.69, "date": "1977-01-01T00:00:00", "highlight": false}, {"Year": 1978, "Country": "United Kingdom", "value": 1.75, "date": "1978-01-01T00:00:00", "highlight": false}, {"Year": 1979, "Country": "United Kingdom", "value": 1.86, "date": "1979-01-01T00:00:00", "highlight": false}, {"Year": 1980, "Country": "United Kingdom", "value": 1.9, "date": "1980-01-01T00:00:00", "highlight": false}, {"Year": 1981, "Country": "United Kingdom", "value": 1.82, "date": "1981-01-01T00:00:00", "highlight": false}, {"Year": 1982, "Country": "United Kingdom", "value": 1.78, "date": "1982-01-01T00:00:00", "highlight": false}, {"Year": 1983, "Country": "United Kingdom", "value": 1.77, "date": "1983-01-01T00:00:00", "highlight": false}, {"Year": 1984, "Country": "United Kingdom", "value": 1.77, "date": "1984-01-01T00:00:00", "highlight": false}, {"Year": 1985, "Country": "United Kingdom", "value": 1.79, "date": "1985-01-01T00:00:00", "highlight": false}, {"Year": 1986, "Country": "United Kingdom", "value": 1.78, "date": "1986-01-01T00:00:00", "highlight": false}, {"Year": 1987, "Country": "United Kingdom", "value": 1.81, "date": "1987-01-01T00:00:00", "highlight": false}, {"Year": 1988, "Country": "United Kingdom", "value": 1.82, "date": "1988-01-01T00:00:00", "highlight": false}, {"Year": 1989, "Country": "United Kingdom", "value": 1.79, "date": "1989-01-01T00:00:00", "highlight": false}, {"Year": 1990, "Country": "United Kingdom", "value": 1.83, "date": "1990-01-01T00:00:00", "highlight": false}, {"Year": 1991, "Country": "United Kingdom", "value": 1.82, "date": "1991-01-01T00:00:00", "highlight": false}, {"Year": 1992, "Country": "United Kingdom", "value": 1.79, "date": "1992-01-01T00:00:00", "highlight": false}, {"Year": 1993, "Country": "United Kingdom", "value": 1.76, "date": "1993-01-01T00:00:00", "highlight": false}, {"Year": 1994, "Country": "United Kingdom", "value": 1.74, "date": "1994-01-01T00:00:00", "highlight": false}, {"Year": 1995, "Country": "United Kingdom", "value": 1.71, "date": "1995-01-01T00:00:00", "highlight": false}, {"Year": 1996, "Country": "United Kingdom", "value": 1.73, "date": "1996-01-01T00:00:00", "highlight": false}, {"Year": 1997, "Country": "United Kingdom", "value": 1.72, "date": "1997-01-01T00:00:00", "highlight": false}, {"Year": 1998, "Country": "United Kingdom", "value": 1.71, "date": "1998-01-01T00:00:00", "highlight": false}, {"Year": 1999, "Country": "United Kingdom", "value": 1.68, "date": "1999-01-01T00:00:00", "highlight": false}, {"Year": 2000, "Country": "United Kingdom", "value": 1.64, "date": "2000-01-01T00:00:00", "highlight": false}, {"Year": 2001, "Country": "United Kingdom", "value": 1.63, "date": "2001-01-01T00:00:00", "highlight": false}, {"Year": 2002, "Country": "United Kingdom", "value": 1.63, "date": "2002-01-01T00:00:00", "highlight": false}, {"Year": 2003, "Country": "United Kingdom", "value": 1.7, "date": "2003-01-01T00:00:00", "highlight": false}, {"Year": 2004, "Country": "United Kingdom", "value": 1.75, "date": "2004-01-01T00:00:00", "highlight": false}, {"Year": 2005, "Country": "United Kingdom", "value": 1.76, "date": "2005-01-01T00:00:00", "highlight": false}, {"Year": 2006, "Country": "United Kingdom", "value": 1.82, "date": "2006-01-01T00:00:00", "highlight": false}, {"Year": 2007, "Country": "United Kingdom", "value": 1.86, "date": "2007-01-01T00:00:00", "highlight": false}, {"Year": 2008, "Country": "United Kingdom", "value": 1.91, "date": "2008-01-01T00:00:00", "highlight": false}, {"Year": 2009, "Country": "United Kingdom", "value": 1.89, "date": "2009-01-01T00:00:00", "highlight": false}, {"Year": 2010, "Country": "United Kingdom", "value": 1.92, "date": "2010-01-01T00:00:00", "highlight": false}, {"Year": 2011, "Country": "United Kingdom", "value": 1.91, "date": "2011-01-01T00:00:00", "highlight": false}, {"Year": 2012, "Country": "United Kingdom", "value": 1.92, "date": "2012-01-01T00:00:00", "highlight": false}, {"Year": 2013, "Country": "United Kingdom", "value": 1.83, "date": "2013-01-01T00:00:00", "highlight": false}, {"Year": 2014, "Country": "United Kingdom", "value": 1.81, "date": "2014-01-01T00:00:00", "highlight": false}, {"Year": 2015, "Country": "United Kingdom", "value": 1.8, "date": "2015-01-01T00:00:00", "highlight": false}, {"Year": 2016, "Country": "United Kingdom", "value": 1.79, "date": "2016-01-01T00:00:00", "highlight": false}, {"Year": 2017, "Country": "United Kingdom", "value": 1.74, "date": "2017-01-01T00:00:00", "highlight": false}, {"Year": 2018, "Country": "United Kingdom", "value": 1.68, "date": "2018-01-01T00:00:00", "highlight": false}, {"Year": 2019, "Country": "United Kingdom", "value": 1.63, "date": "2019-01-01T00:00:00", "highlight": false}, {"Year": 2020, "Country": "United Kingdom", "value": 1.56, "date": "2020-01-01T00:00:00", "highlight": false}, {"Year": 2021, "Country": "United Kingdom", "value": 1.56, "date": "2021-01-01T00:00:00", "highlight": false}, {"Year": 2022, "Country": "United Kingdom", "value": 1.57, "date": "2022-01-01T00:00:00", "highlight": true}, {"Year": 1960, "Country": "United States", "value": 3.654, "date": "1960-01-01T00:00:00", "highlight": false}, {"Year": 1961, "Country": "United States", "value": 3.62, "date": "1961-01-01T00:00:00", "highlight": false}, {"Year": 1962, "Country": "United States", "value": 3.461, "date": "1962-01-01T00:00:00", "highlight": false}, {"Year": 1963, "Country": "United States", "value": 3.319, "date": "1963-01-01T00:00:00", "highlight": false}, {"Year": 1964, "Country": "United States", "value": 3.19, "date": "1964-01-01T00:00:00", "highlight": false}, {"Year": 1965, "Country": "United States", "value": 2.913, "date": "1965-01-01T00:00:00", "highlight": false}, {"Year": 1966, "Country": "United States", "value": 2.721, "date": "1966-01-01T00:00:00", "highlight": false}, {"Year": 1967, "Country": "United States", "value": 2.558, "date": "1967-01-01T00:00:00", "highlight": false}, {"Year": 1968, "Country": "United States", "value": 2.464, "date": "1968-01-01T00:00:00", "highlight": false}, {"Year": 1969, "Country": "United States", "value": 2.456, "date": "1969-01-01T00:00:00", "highlight": false}, {"Year": 1970, "Country": "United States", "value": 2.48, "date": "1970-01-01T00:00:00", "highlight": false}, {"Year": 1971, "Country": "United States", "value": 2.266, "date": "1971-01-01T00:00:00", "highlight": false}, {"Year": 1972, "Country": "United States", "value": 2.01, "date": "1972-01-01T00:00:00", "highlight": false}, {"Year": 1973, "Country": "United States", "value": 1.879, "date": "1973-01-01T00:00:00", "highlight": false}, {"Year": 1974, "Country": "United States", "value": 1.835, "date": "1974-01-01T00:00:00", "highlight": false}, {"Year": 1975, "Country": "United States", "value": 1.774, "date": "1975-01-01T00:00:00", "highlight": false}, {"Year": 1976, "Country": "United States", "value": 1.738, "date": "1976-01-01T00:00:00", "highlight": false}, {"Year": 1977, "Country": "United States", "value": 1.79, "date": "1977-01-01T00:00:00", "highlight": false}, {"Year": 1978, "Country": "United States", "value": 1.76, "date": "1978-01-01T00:00:00", "highlight": false}, {"Year": 1979, "Country": "United States", "value": 1.808, "date": "1979-01-01T00:00:00", "highlight": false}, {"Year": 1980, "Country": "United States", "value": 1.839, "date": "1980-01-01T00:00:00", "highlight": false}, {"Year": 1981, "Country": "United States", "value": 1.812, "date": "1981-01-01T00:00:00", "highlight": false}, {"Year": 1982, "Country": "United States", "value": 1.827, "date": "1982-01-01T00:00:00", "highlight": false}, {"Year": 1983, "Country": "United States", "value": 1.799, "date": "1983-01-01T00:00:00", "highlight": false}, {"Year": 1984, "Country": "United States", "value": 1.806, "date": "1984-01-01T00:00:00", "highlight": false}, {"Year": 1985, "Country": "United States", "value": 1.844, "date": "1985-01-01T00:00:00", "highlight": false}, {"Year": 1986, "Country": "United States", "value": 1.837, "date": "1986-01-01T00:00:00", "highlight": false}, {"Year": 1987, "Country": "United States", "value": 1.872, "date": "1987-01-01T00:00:00", "highlight": false}, {"Year": 1988, "Country": "United States", "value": 1.934, "date": "1988-01-01T00:00:00", "highlight": false}, {"Year": 1989, "Country": "United States", "value": 2.014, "date": "1989-01-01T00:00:00", "highlight": false}, {"Year": 1990, "Country": "United States", "value": 2.081, "date": "1990-01-01T00:00:00", "highlight": false}, {"Year": 1991, "Country": "United States", "value": 2.063, "date": "1991-01-01T00:00:00", "highlight": false}, {"Year": 1992, "Country": "United States", "value": 2.046, "date": "1992-01-01T00:00:00", "highlight": false}, {"Year": 1993, "Country": "United States", "value": 2.019, "date": "1993-01-01T00:00:00", "highlight": false}, {"Year": 1994, "Country": "United States", "value": 2.002, "date": "1994-01-01T00:00:00", "highlight": false}, {"Year": 1995, "Country": "United States", "value": 1.978, "date": "1995-01-01T00:00:00", "highlight": false}, {"Year": 1996, "Country": "United States", "value": 1.976, "date": "1996-01-01T00:00:00", "highlight": false}, {"Year": 1997, "Country": "United States", "value": 1.971, "date": "1997-01-01T00:00:00", "highlight": false}, {"Year": 1998, "Country": "United States", "value": 1.999, "date": "1998-01-01T00:00:00", "highlight": false}, {"Year": 1999, "Country": "United States", "value": 2.007, "date": "1999-01-01T00:00:00", "highlight": false}, {"Year": 2000, "Country": "United States", "value": 2.056, "date": "2000-01-01T00:00:00", "highlight": false}, {"Year": 2001, "Country": "United States", "value": 2.03, "date": "2001-01-01T00:00:00", "highlight": false}, {"Year": 2002, "Country": "United States", "value": 2.021, "date": "2002-01-01T00:00:00", "highlight": false}, {"Year": 2003, "Country": "United States", "value": 2.047, "date": "2003-01-01T00:00:00", "highlight": false}, {"Year": 2004, "Country": "United States", "value": 2.051, "date": "2004-01-01T00:00:00", "highlight": false}, {"Year": 2005, "Country": "United States", "value": 2.057, "date": "2005-01-01T00:00:00", "highlight": false}, {"Year": 2006, "Country": "United States", "value": 2.108, "date": "2006-01-01T00:00:00", "highlight": false}, {"Year": 2007, "Country": "United States", "value": 2.12, "date": "2007-01-01T00:00:00", "highlight": false}, {"Year": 2008, "Country": "United States", "value": 2.072, "date": "2008-01-01T00:00:00", "highlight": false}, {"Year": 2009, "Country": "United States", "value": 2.002, "date": "2009-01-01T00:00:00", "highlight": false}, {"Year": 2010, "Country": "United States", "value": 1.931, "date": "2010-01-01T00:00:00", "highlight": false}, {"Year": 2011, "Country": "United States", "value": 1.895, "date": "2011-01-01T00:00:00", "highlight": false}, {"Year": 2012, "Country": "United States", "value": 1.881, "date": "2012-01-01T00:00:00", "highlight": false}, {"Year": 2013, "Country": "United States", "value": 1.857, "date": "2013-01-01T00:00:00", "highlight": false}, {"Year": 2014, "Country": "United States", "value": 1.863, "date": "2014-01-01T00:00:00", "highlight": false}, {"Year": 2015, "Country": "United States", "value": 1.843, "date": "2015-01-01T00:00:00", "highlight": false}, {"Year": 2016, "Country": "United States", "value": 1.821, "date": "2016-01-01T00:00:00", "highlight": false}, {"Year": 2017, "Country": "United States", "value": 1.766, "date": "2017-01-01T00:00:00", "highlight": false}, {"Year": 2018, "Country": "United States", "value": 1.73, "date": "2018-01-01T00:00:00", "highlight": false}, {"Year": 2019, "Country": "United States", "value": 1.706, "date": "2019-01-01T00:00:00", "highlight": false}, {"Year": 2020, "Country": "United States", "value": 1.641, "date": "2020-01-01T00:00:00", "highlight": false}, {"Year": 2021, "Country": "United States", "value": 1.664, "date": "2021-01-01T00:00:00", "highlight": false}, {"Year": 2022, "Country": "United States", "value": 1.665, "date": "2022-01-01T00:00:00", "highlight": true}, {"Year": 1960, "Country": "World", "value": 4.69, "date": "1960-01-01T00:00:00", "highlight": false}, {"Year": 1961, "Country": "World", "value": 4.569, "date": "1961-01-01T00:00:00", "highlight": false}, {"Year": 1962, "Country": "World", "value": 5.029, "date": "1962-01-01T00:00:00", "highlight": false}, {"Year": 1963, "Country": "World", "value": 5.317, "date": "1963-01-01T00:00:00", "highlight": false}, {"Year": 1964, "Country": "World", "value": 5.134, "date": "1964-01-01T00:00:00", "highlight": false}, {"Year": 1965, "Country": "World", "value": 5.086, "date": "1965-01-01T00:00:00", "highlight": false}, {"Year": 1966, "Country": "World", "value": 4.97, "date": "1966-01-01T00:00:00", "highlight": false}, {"Year": 1967, "Country": "World", "value": 4.866, "date": "1967-01-01T00:00:00", "highlight": false}, {"Year": 1968, "Country": "World", "value": 4.978, "date": "1968-01-01T00:00:00", "highlight": false}, {"Year": 1969, "Country": "World", "value": 4.882, "date": "1969-01-01T00:00:00", "highlight": false}, {"Year": 1970, "Country": "World", "value": 4.842, "date": "1970-01-01T00:00:00", "highlight": false}, {"Year": 1971, "Country": "World", "value": 4.692, "date": "1971-01-01T00:00:00", "highlight": false}, {"Year": 1972, "Country": "World", "value": 4.55, "date": "1972-01-01T00:00:00", "highlight": false}, {"Year": 1973, "Country": "World", "value": 4.42, "date": "1973-01-01T00:00:00", "highlight": false}, {"Year": 1974, "Country": "World", "value": 4.259, "date": "1974-01-01T00:00:00", "highlight": false}, {"Year": 1975, "Country": "World", "value": 4.076, "date": "1975-01-01T00:00:00", "highlight": false}, {"Year": 1976, "Country": "World", "value": 3.969, "date": "1976-01-01T00:00:00", "highlight": false}, {"Year": 1977, "Country": "World", "value": 3.844, "date": "1977-01-01T00:00:00", "highlight": false}, {"Year": 1978, "Country": "World", "value": 3.777, "date": "1978-01-01T00:00:00", "highlight": false}, {"Year": 1979, "Country": "World", "value": 3.76, "date": "1979-01-01T00:00:00", "highlight": false}, {"Year": 1980, "Country": "World", "value": 3.734, "date": "1980-01-01T00:00:00", "highlight": false}, {"Year": 1981, "Country": "World", "value": 3.707, "date": "1981-01-01T00:00:00", "highlight": false}, {"Year": 1982, "Country": "World", "value": 3.723, "date": "1982-01-01T00:00:00", "highlight": false}, {"Year": 1983, "Country": "World", "value": 3.594, "date": "1983-01-01T00:00:00", "highlight": false}, {"Year": 1984, "Country": "World", "value": 3.569, "date": "1984-01-01T00:00:00", "highlight": false}, {"Year": 1985, "Country": "World", "value": 3.532, "date": "1985-01-01T00:00:00", "highlight": false}, {"Year": 1986, "Country": "World", "value": 3.518, "date": "1986-01-01T00:00:00", "highlight": false}, {"Year": 1987, "Country": "World", "value": 3.489, "date": "1987-01-01T00:00:00", "highlight": false}, {"Year": 1988, "Country": "World", "value": 3.398, "date": "1988-01-01T00:00:00", "highlight": false}, {"Year": 1989, "Country": "World", "value": 3.348, "date": "1989-01-01T00:00:00", "highlight": false}, {"Year": 1990, "Country": "World", "value": 3.308, "date": "1990-01-01T00:00:00", "highlight": false}, {"Year": 1991, "Country": "World", "value": 3.127, "date": "1991-01-01T00:00:00", "highlight": false}, {"Year": 1992, "Country": "World", "value": 3.041, "date": "1992-01-01T00:00:00", "highlight": false}, {"Year": 1993, "Country": "World", "value": 2.973, "date": "1993-01-01T00:00:00", "highlight": false}, {"Year": 1994, "Country": "World", "value": 2.92, "date": "1994-01-01T00:00:00", "highlight": false}, {"Year": 1995, "Country": "World", "value": 2.866, "date": "1995-01-01T00:00:00", "highlight": false}, {"Year": 1996, "Country": "World", "value": 2.818, "date": "1996-01-01T00:00:00", "highlight": false}, {"Year": 1997, "Country": "World", "value": 2.777, "date": "1997-01-01T00:00:00", "highlight": false}, {"Year": 1998, "Country": "World", "value": 2.742, "date": "1998-01-01T00:00:00", "highlight": false}, {"Year": 1999, "Country": "World", "value": 2.715, "date": "1999-01-01T00:00:00", "highlight": false}, {"Year": 2000, "Country": "World", "value": 2.724, "date": "2000-01-01T00:00:00", "highlight": false}, {"Year": 2001, "Country": "World", "value": 2.686, "date": "2001-01-01T00:00:00", "highlight": false}, {"Year": 2002, "Country": "World", "value": 2.659, "date": "2002-01-01T00:00:00", "highlight": false}, {"Year": 2003, "Country": "World", "value": 2.636, "date": "2003-01-01T00:00:00", "highlight": false}, {"Year": 2004, "Country": "World", "value": 2.628, "date": "2004-01-01T00:00:00", "highlight": false}, {"Year": 2005, "Country": "World", "value": 2.609, "date": "2005-01-01T00:00:00", "highlight": false}, {"Year": 2006, "Country": "World", "value": 2.602, "date": "2006-01-01T00:00:00", "highlight": false}, {"Year": 2007, "Country": "World", "value": 2.601, "date": "2007-01-01T00:00:00", "highlight": false}, {"Year": 2008, "Country": "World", "value": 2.601, "date": "2008-01-01T00:00:00", "highlight": false}, {"Year": 2009, "Country": "World", "value": 2.587, "date": "2009-01-01T00:00:00", "highlight": false}, {"Year": 2010, "Country": "World", "value": 2.563, "date": "2010-01-01T00:00:00", "highlight": false}, {"Year": 2011, "Country": "World", "value": 2.542, "date": "2011-01-01T00:00:00", "highlight": false}, {"Year": 2012, "Country": "World", "value": 2.558, "date": "2012-01-01T00:00:00", "highlight": false}, {"Year": 2013, "Country": "World", "value": 2.522, "date": "2013-01-01T00:00:00", "highlight": false}, {"Year": 2014, "Country": "World", "value": 2.514, "date": "2014-01-01T00:00:00", "highlight": false}, {"Year": 2015, "Country": "World", "value": 2.486, "date": "2015-01-01T00:00:00", "highlight": false}, {"Year": 2016, "Country": "World", "value": 2.489, "date": "2016-01-01T00:00:00", "highlight": false}, {"Year": 2017, "Country": "World", "value": 2.467, "date": "2017-01-01T00:00:00", "highlight": false}, {"Year": 2018, "Country": "World", "value": 2.405, "date": "2018-01-01T00:00:00", "highlight": false}, {"Year": 2019, "Country": "World", "value": 2.368, "date": "2019-01-01T00:00:00", "highlight": false}, {"Year": 2020, "Country": "World", "value": 2.308, "date": "2020-01-01T00:00:00", "highlight": false}, {"Year": 2021, "Country": "World", "value": 2.282, "date": "2021-01-01T00:00:00", "highlight": false}, {"Year": 2022, "Country": "World", "value": 2.268, "date": "2022-01-01T00:00:00", "highlight": true}]}}