{"config": {"font": "Circular Std", "mark": {"line": {"interpolate": "monotone"}}, "view": {"stroke": "transparent", "width": 400, "height": 300}, "range": {"category": ["#36B7B4", "#E6224B", "#F4C245", "#0063AF", "#00A767", "#179FDB", "#EB5C2E"], "diverging": ["#E6224B", "#E54753", "#C9C9C9", "#179FDB", "#122B39"], "heatmap": ["#C9C9C9", "#179FDB", "#0063AF", "#122B39"], "ordinal": ["#00A767", "#36B7B4", "#179FDB", "#0063AF", "#243B5A"]}, "axisX": {"domainColor": "#676A86", "domainOpacity": 0.5, "grid": false, "labelAngle": 0, "labelColor": "#676A86", "labelOpacity": 0.7, "orient": "bottom", "tickColor": "#676A86", "tickCount": 10, "tickOpacity": 0.5, "title": false, "titleAlign": "center", "titleAnchor": "middle", "titleColor": "#676A86", "titleFontSize": 12, "titleOpacity": 0.8, "titleY": -15}, "axisY": {"domainColor": "#676A86", "domainOpacity": 0.5, "gridColor": "#676A86", "gridDash": [1, 5], "gridOpacity": 0.5, "labelColor": "#676A86", "labelOpacity": 0.7, "labelPadding": 5, "tickColor": "#676A86", "tickCount": 8, "tickOpacity": 0.5, "ticks": false, "titleAlign": "left", "titleAngle": 0, "titleBaseline": "bottom", "titleColor": "#676A86", "titleFontSize": 12, "titleOpacity": 0.8, "titleX": 0, "titleY": -7}}, "vconcat": [{"data": {"name": "data-dfe0380c33c05464e67866c7c2a83881"}, "mark": {"type": "line", "color": "#36B7B4"}, "encoding": {"tooltip": [{"field": "date", "title": "Date", "type": "temporal"}, {"field": "value", "format": ".2f", "title": "Value", "type": "quantitative"}], "x": {"field": "date", "type": "temporal"}, "y": {"axis": {"format": "%"}, "field": "value", "title": "Debt, % of GDP", "type": "quantitative"}}, "height": 200, "width": 500}, {"data": {"name": "data-f2d687ca02b6c70826dbff1fc4d1c1d4"}, "mark": {"type": "bar"}, "encoding": {"color": {"condition": {"test": "(datum.value > 0)", "value": "#E6224B"}, "value": "#36B7B4"}, "tooltip": [{"field": "date", "title": "Date", "type": "temporal"}, {"field": "value", "format": ".2f", "title": "Value", "type": "quantitative"}], "x": {"field": "date", "type": "temporal"}, "y": {"axis": {"format": "%"}, "field": "value", "title": "Deficit, % of GDP", "type": "quantitative"}}, "height": 150, "width": 500}], "resolve": {"scale": {"x": "shared"}}, "$schema": "https://vega.github.io/schema/vega-lite/v5.8.0.json", "datasets": {"data-dfe0380c33c05464e67866c7c2a83881": [{"date": "1993-03-01T00:00:00", "value": 0.267, "series": "debt"}, {"date": "1993-04-01T00:00:00", "value": 0.276, "series": "debt"}, {"date": "1993-05-01T00:00:00", "value": 0.281, "series": "debt"}, {"date": "1993-06-01T00:00:00", "value": 0.281, "series": "debt"}, {"date": "1993-07-01T00:00:00", "value": 0.285, "series": "debt"}, {"date": "1993-08-01T00:00:00", "value": 0.289, "series": "debt"}, {"date": "1993-09-01T00:00:00", "value": 0.294, "series": "debt"}, {"date": "1993-10-01T00:00:00", "value": 0.293, "series": "debt"}, {"date": "1993-11-01T00:00:00", "value": 0.293, "series": "debt"}, {"date": "1993-12-01T00:00:00", "value": 0.297, "series": "debt"}, {"date": "1994-01-01T00:00:00", "value": 0.29600000000000004, "series": "debt"}, {"date": "1994-02-01T00:00:00", "value": 0.299, "series": "debt"}, {"date": "1994-03-01T00:00:00", "value": 0.312, "series": "debt"}, {"date": "1994-04-01T00:00:00", "value": 0.316, "series": "debt"}, {"date": "1994-05-01T00:00:00", "value": 0.321, "series": "debt"}, {"date": "1994-06-01T00:00:00", "value": 0.325, "series": "debt"}, {"date": "1994-07-01T00:00:00", "value": 0.326, "series": "debt"}, {"date": "1994-08-01T00:00:00", "value": 0.32899999999999996, "series": "debt"}, {"date": "1994-09-01T00:00:00", "value": 0.33399999999999996, "series": "debt"}, {"date": "1994-10-01T00:00:00", "value": 0.33399999999999996, "series": "debt"}, {"date": "1994-11-01T00:00:00", "value": 0.336, "series": "debt"}, {"date": "1994-12-01T00:00:00", "value": 0.336, "series": "debt"}, {"date": "1995-01-01T00:00:00", "value": 0.331, "series": "debt"}, {"date": "1995-02-01T00:00:00", "value": 0.336, "series": "debt"}, {"date": "1995-03-01T00:00:00", "value": 0.34600000000000003, "series": "debt"}, {"date": "1995-04-01T00:00:00", "value": 0.349, "series": "debt"}, {"date": "1995-05-01T00:00:00", "value": 0.35200000000000004, "series": "debt"}, {"date": "1995-06-01T00:00:00", "value": 0.355, "series": "debt"}, {"date": "1995-07-01T00:00:00", "value": 0.354, "series": "debt"}, {"date": "1995-08-01T00:00:00", "value": 0.35700000000000004, "series": "debt"}, {"date": "1995-09-01T00:00:00", "value": 0.36, "series": "debt"}, {"date": "1995-10-01T00:00:00", "value": 0.35700000000000004, "series": "debt"}, {"date": "1995-11-01T00:00:00", "value": 0.359, "series": "debt"}, {"date": "1995-12-01T00:00:00", "value": 0.35700000000000004, "series": "debt"}, {"date": "1996-01-01T00:00:00", "value": 0.349, "series": "debt"}, {"date": "1996-02-01T00:00:00", "value": 0.35100000000000003, "series": "debt"}, {"date": "1996-03-01T00:00:00", "value": 0.361, "series": "debt"}, {"date": "1996-04-01T00:00:00", "value": 0.36200000000000004, "series": "debt"}, {"date": "1996-05-01T00:00:00", "value": 0.365, "series": "debt"}, {"date": "1996-06-01T00:00:00", "value": 0.36700000000000005, "series": "debt"}, {"date": "1996-07-01T00:00:00", "value": 0.363, "series": "debt"}, {"date": "1996-08-01T00:00:00", "value": 0.36700000000000005, "series": "debt"}, {"date": "1996-09-01T00:00:00", "value": 0.369, "series": "debt"}, {"date": "1996-10-01T00:00:00", "value": 0.363, "series": "debt"}, {"date": "1996-11-01T00:00:00", "value": 0.365, "series": "debt"}, {"date": "1996-12-01T00:00:00", "value": 0.36700000000000005, "series": "debt"}, {"date": "1997-01-01T00:00:00", "value": 0.358, "series": "debt"}, {"date": "1997-02-01T00:00:00", "value": 0.359, "series": "debt"}, {"date": "1997-03-01T00:00:00", "value": 0.36700000000000005, "series": "debt"}, {"date": "1997-04-01T00:00:00", "value": 0.37200000000000005, "series": "debt"}, {"date": "1997-05-01T00:00:00", "value": 0.376, "series": "debt"}, {"date": "1997-06-01T00:00:00", "value": 0.382, "series": "debt"}, {"date": "1997-07-01T00:00:00", "value": 0.377, "series": "debt"}, {"date": "1997-08-01T00:00:00", "value": 0.37799999999999995, "series": "debt"}, {"date": "1997-09-01T00:00:00", "value": 0.379, "series": "debt"}, {"date": "1997-10-01T00:00:00", "value": 0.37200000000000005, "series": "debt"}, {"date": "1997-11-01T00:00:00", "value": 0.375, "series": "debt"}, {"date": "1997-12-01T00:00:00", "value": 0.374, "series": "debt"}, {"date": "1998-01-01T00:00:00", "value": 0.363, "series": "debt"}, {"date": "1998-02-01T00:00:00", "value": 0.361, "series": "debt"}, {"date": "1998-03-01T00:00:00", "value": 0.366, "series": "debt"}, {"date": "1998-04-01T00:00:00", "value": 0.36200000000000004, "series": "debt"}, {"date": "1998-05-01T00:00:00", "value": 0.363, "series": "debt"}, {"date": "1998-06-01T00:00:00", "value": 0.368, "series": "debt"}, {"date": "1998-07-01T00:00:00", "value": 0.36200000000000004, "series": "debt"}, {"date": "1998-08-01T00:00:00", "value": 0.36200000000000004, "series": "debt"}, {"date": "1998-09-01T00:00:00", "value": 0.363, "series": "debt"}, {"date": "1998-10-01T00:00:00", "value": 0.354, "series": "debt"}, {"date": "1998-11-01T00:00:00", "value": 0.35600000000000004, "series": "debt"}, {"date": "1998-12-01T00:00:00", "value": 0.35700000000000004, "series": "debt"}, {"date": "1999-01-01T00:00:00", "value": 0.345, "series": "debt"}, {"date": "1999-02-01T00:00:00", "value": 0.345, "series": "debt"}, {"date": "1999-03-01T00:00:00", "value": 0.35100000000000003, "series": "debt"}, {"date": "1999-04-01T00:00:00", "value": 0.34700000000000003, "series": "debt"}, {"date": "1999-05-01T00:00:00", "value": 0.348, "series": "debt"}, {"date": "1999-06-01T00:00:00", "value": 0.35200000000000004, "series": "debt"}, {"date": "1999-07-01T00:00:00", "value": 0.345, "series": "debt"}, {"date": "1999-08-01T00:00:00", "value": 0.34299999999999997, "series": "debt"}, {"date": "1999-09-01T00:00:00", "value": 0.342, "series": "debt"}, {"date": "1999-10-01T00:00:00", "value": 0.332, "series": "debt"}, {"date": "1999-11-01T00:00:00", "value": 0.331, "series": "debt"}, {"date": "1999-12-01T00:00:00", "value": 0.34299999999999997, "series": "debt"}, {"date": "2000-01-01T00:00:00", "value": 0.324, "series": "debt"}, {"date": "2000-02-01T00:00:00", "value": 0.32, "series": "debt"}, {"date": "2000-03-01T00:00:00", "value": 0.325, "series": "debt"}, {"date": "2000-04-01T00:00:00", "value": 0.317, "series": "debt"}, {"date": "2000-05-01T00:00:00", "value": 0.305, "series": "debt"}, {"date": "2000-06-01T00:00:00", "value": 0.311, "series": "debt"}, {"date": "2000-07-01T00:00:00", "value": 0.302, "series": "debt"}, {"date": "2000-08-01T00:00:00", "value": 0.301, "series": "debt"}, {"date": "2000-09-01T00:00:00", "value": 0.293, "series": "debt"}, {"date": "2000-10-01T00:00:00", "value": 0.28600000000000003, "series": "debt"}, {"date": "2000-11-01T00:00:00", "value": 0.28800000000000003, "series": "debt"}, {"date": "2000-12-01T00:00:00", "value": 0.29600000000000004, "series": "debt"}, {"date": "2001-01-01T00:00:00", "value": 0.281, "series": "debt"}, {"date": "2001-02-01T00:00:00", "value": 0.278, "series": "debt"}, {"date": "2001-03-01T00:00:00", "value": 0.28300000000000003, "series": "debt"}, {"date": "2001-04-01T00:00:00", "value": 0.27899999999999997, "series": "debt"}, {"date": "2001-05-01T00:00:00", "value": 0.282, "series": "debt"}, {"date": "2001-06-01T00:00:00", "value": 0.28800000000000003, "series": "debt"}, {"date": "2001-07-01T00:00:00", "value": 0.281, "series": "debt"}, {"date": "2001-08-01T00:00:00", "value": 0.28, "series": "debt"}, {"date": "2001-09-01T00:00:00", "value": 0.282, "series": "debt"}, {"date": "2001-10-01T00:00:00", "value": 0.276, "series": "debt"}, {"date": "2001-11-01T00:00:00", "value": 0.28, "series": "debt"}, {"date": "2001-12-01T00:00:00", "value": 0.28800000000000003, "series": "debt"}, {"date": "2002-01-01T00:00:00", "value": 0.278, "series": "debt"}, {"date": "2002-02-01T00:00:00", "value": 0.275, "series": "debt"}, {"date": "2002-03-01T00:00:00", "value": 0.281, "series": "debt"}, {"date": "2002-04-01T00:00:00", "value": 0.27899999999999997, "series": "debt"}, {"date": "2002-05-01T00:00:00", "value": 0.28, "series": "debt"}, {"date": "2002-06-01T00:00:00", "value": 0.285, "series": "debt"}, {"date": "2002-07-01T00:00:00", "value": 0.27899999999999997, "series": "debt"}, {"date": "2002-08-01T00:00:00", "value": 0.281, "series": "debt"}, {"date": "2002-09-01T00:00:00", "value": 0.284, "series": "debt"}, {"date": "2002-10-01T00:00:00", "value": 0.28300000000000003, "series": "debt"}, {"date": "2002-11-01T00:00:00", "value": 0.29, "series": "debt"}, {"date": "2002-12-01T00:00:00", "value": 0.301, "series": "debt"}, {"date": "2003-01-01T00:00:00", "value": 0.29, "series": "debt"}, {"date": "2003-02-01T00:00:00", "value": 0.289, "series": "debt"}, {"date": "2003-03-01T00:00:00", "value": 0.298, "series": "debt"}, {"date": "2003-04-01T00:00:00", "value": 0.295, "series": "debt"}, {"date": "2003-05-01T00:00:00", "value": 0.295, "series": "debt"}, {"date": "2003-06-01T00:00:00", "value": 0.298, "series": "debt"}, {"date": "2003-07-01T00:00:00", "value": 0.294, "series": "debt"}, {"date": "2003-08-01T00:00:00", "value": 0.29600000000000004, "series": "debt"}, {"date": "2003-09-01T00:00:00", "value": 0.301, "series": "debt"}, {"date": "2003-10-01T00:00:00", "value": 0.3, "series": "debt"}, {"date": "2003-11-01T00:00:00", "value": 0.304, "series": "debt"}, {"date": "2003-12-01T00:00:00", "value": 0.314, "series": "debt"}, {"date": "2004-01-01T00:00:00", "value": 0.301, "series": "debt"}, {"date": "2004-02-01T00:00:00", "value": 0.3, "series": "debt"}, {"date": "2004-03-01T00:00:00", "value": 0.309, "series": "debt"}, {"date": "2004-04-01T00:00:00", "value": 0.315, "series": "debt"}, {"date": "2004-05-01T00:00:00", "value": 0.318, "series": "debt"}, {"date": "2004-06-01T00:00:00", "value": 0.325, "series": "debt"}, {"date": "2004-07-01T00:00:00", "value": 0.319, "series": "debt"}, {"date": "2004-08-01T00:00:00", "value": 0.32, "series": "debt"}, {"date": "2004-09-01T00:00:00", "value": 0.326, "series": "debt"}, {"date": "2004-10-01T00:00:00", "value": 0.32299999999999995, "series": "debt"}, {"date": "2004-11-01T00:00:00", "value": 0.331, "series": "debt"}, {"date": "2004-12-01T00:00:00", "value": 0.341, "series": "debt"}, {"date": "2005-01-01T00:00:00", "value": 0.327, "series": "debt"}, {"date": "2005-02-01T00:00:00", "value": 0.326, "series": "debt"}, {"date": "2005-03-01T00:00:00", "value": 0.335, "series": "debt"}, {"date": "2005-04-01T00:00:00", "value": 0.331, "series": "debt"}, {"date": "2005-05-01T00:00:00", "value": 0.332, "series": "debt"}, {"date": "2005-06-01T00:00:00", "value": 0.33799999999999997, "series": "debt"}, {"date": "2005-07-01T00:00:00", "value": 0.332, "series": "debt"}, {"date": "2005-08-01T00:00:00", "value": 0.33399999999999996, "series": "debt"}, {"date": "2005-09-01T00:00:00", "value": 0.341, "series": "debt"}, {"date": "2005-10-01T00:00:00", "value": 0.336, "series": "debt"}, {"date": "2005-11-01T00:00:00", "value": 0.341, "series": "debt"}, {"date": "2005-12-01T00:00:00", "value": 0.35100000000000003, "series": "debt"}, {"date": "2006-01-01T00:00:00", "value": 0.33399999999999996, "series": "debt"}, {"date": "2006-02-01T00:00:00", "value": 0.335, "series": "debt"}, {"date": "2006-03-01T00:00:00", "value": 0.34299999999999997, "series": "debt"}, {"date": "2006-04-01T00:00:00", "value": 0.341, "series": "debt"}, {"date": "2006-05-01T00:00:00", "value": 0.345, "series": "debt"}, {"date": "2006-06-01T00:00:00", "value": 0.353, "series": "debt"}, {"date": "2006-07-01T00:00:00", "value": 0.344, "series": "debt"}, {"date": "2006-08-01T00:00:00", "value": 0.34600000000000003, "series": "debt"}, {"date": "2006-09-01T00:00:00", "value": 0.353, "series": "debt"}, {"date": "2006-10-01T00:00:00", "value": 0.34700000000000003, "series": "debt"}, {"date": "2006-11-01T00:00:00", "value": 0.35100000000000003, "series": "debt"}, {"date": "2006-12-01T00:00:00", "value": 0.359, "series": "debt"}, {"date": "2007-01-01T00:00:00", "value": 0.34299999999999997, "series": "debt"}, {"date": "2007-02-01T00:00:00", "value": 0.341, "series": "debt"}, {"date": "2007-03-01T00:00:00", "value": 0.35100000000000003, "series": "debt"}, {"date": "2007-04-01T00:00:00", "value": 0.348, "series": "debt"}, {"date": "2007-05-01T00:00:00", "value": 0.35100000000000003, "series": "debt"}, {"date": "2007-06-01T00:00:00", "value": 0.35700000000000004, "series": "debt"}, {"date": "2007-07-01T00:00:00", "value": 0.34700000000000003, "series": "debt"}, {"date": "2007-08-01T00:00:00", "value": 0.349, "series": "debt"}, {"date": "2007-09-01T00:00:00", "value": 0.353, "series": "debt"}, {"date": "2007-10-01T00:00:00", "value": 0.349, "series": "debt"}, {"date": "2007-11-01T00:00:00", "value": 0.354, "series": "debt"}, {"date": "2007-12-01T00:00:00", "value": 0.363, "series": "debt"}, {"date": "2008-01-01T00:00:00", "value": 0.348, "series": "debt"}, {"date": "2008-02-01T00:00:00", "value": 0.35100000000000003, "series": "debt"}, {"date": "2008-03-01T00:00:00", "value": 0.35600000000000004, "series": "debt"}, {"date": "2008-04-01T00:00:00", "value": 0.358, "series": "debt"}, {"date": "2008-05-01T00:00:00", "value": 0.365, "series": "debt"}, {"date": "2008-06-01T00:00:00", "value": 0.377, "series": "debt"}, {"date": "2008-07-01T00:00:00", "value": 0.379, "series": "debt"}, {"date": "2008-08-01T00:00:00", "value": 0.396, "series": "debt"}, {"date": "2008-09-01T00:00:00", "value": 0.43, "series": "debt"}, {"date": "2008-10-01T00:00:00", "value": 0.43700000000000006, "series": "debt"}, {"date": "2008-11-01T00:00:00", "value": 0.446, "series": "debt"}, {"date": "2008-12-01T00:00:00", "value": 0.479, "series": "debt"}, {"date": "2009-01-01T00:00:00", "value": 0.48, "series": "debt"}, {"date": "2009-02-01T00:00:00", "value": 0.48700000000000004, "series": "debt"}, {"date": "2009-03-01T00:00:00", "value": 0.506, "series": "debt"}, {"date": "2009-04-01T00:00:00", "value": 0.517, "series": "debt"}, {"date": "2009-05-01T00:00:00", "value": 0.531, "series": "debt"}, {"date": "2009-06-01T00:00:00", "value": 0.5489999999999999, "series": "debt"}, {"date": "2009-07-01T00:00:00", "value": 0.551, "series": "debt"}, {"date": "2009-08-01T00:00:00", "value": 0.552, "series": "debt"}, {"date": "2009-09-01T00:00:00", "value": 0.564, "series": "debt"}, {"date": "2009-10-01T00:00:00", "value": 0.5670000000000001, "series": "debt"}, {"date": "2009-11-01T00:00:00", "value": 0.575, "series": "debt"}, {"date": "2009-12-01T00:00:00", "value": 0.61, "series": "debt"}, {"date": "2010-01-01T00:00:00", "value": 0.631, "series": "debt"}, {"date": "2010-02-01T00:00:00", "value": 0.633, "series": "debt"}, {"date": "2010-03-01T00:00:00", "value": 0.647, "series": "debt"}, {"date": "2010-04-01T00:00:00", "value": 0.648, "series": "debt"}, {"date": "2010-05-01T00:00:00", "value": 0.653, "series": "debt"}, {"date": "2010-06-01T00:00:00", "value": 0.664, "series": "debt"}, {"date": "2010-07-01T00:00:00", "value": 0.664, "series": "debt"}, {"date": "2010-08-01T00:00:00", "value": 0.667, "series": "debt"}, {"date": "2010-09-01T00:00:00", "value": 0.68, "series": "debt"}, {"date": "2010-10-01T00:00:00", "value": 0.68, "series": "debt"}, {"date": "2010-11-01T00:00:00", "value": 0.6890000000000001, "series": "debt"}, {"date": "2010-12-01T00:00:00", "value": 0.703, "series": "debt"}, {"date": "2011-01-01T00:00:00", "value": 0.693, "series": "debt"}, {"date": "2011-02-01T00:00:00", "value": 0.696, "series": "debt"}, {"date": "2011-03-01T00:00:00", "value": 0.7090000000000001, "series": "debt"}, {"date": "2011-04-01T00:00:00", "value": 0.71, "series": "debt"}, {"date": "2011-05-01T00:00:00", "value": 0.7140000000000001, "series": "debt"}, {"date": "2011-06-01T00:00:00", "value": 0.7240000000000001, "series": "debt"}, {"date": "2011-07-01T00:00:00", "value": 0.718, "series": "debt"}, {"date": "2011-08-01T00:00:00", "value": 0.726, "series": "debt"}, {"date": "2011-09-01T00:00:00", "value": 0.7290000000000001, "series": "debt"}, {"date": "2011-10-01T00:00:00", "value": 0.727, "series": "debt"}, {"date": "2011-11-01T00:00:00", "value": 0.731, "series": "debt"}, {"date": "2011-12-01T00:00:00", "value": 0.742, "series": "debt"}, {"date": "2012-01-01T00:00:00", "value": 0.731, "series": "debt"}, {"date": "2012-02-01T00:00:00", "value": 0.7340000000000001, "series": "debt"}, {"date": "2012-03-01T00:00:00", "value": 0.743, "series": "debt"}, {"date": "2012-04-01T00:00:00", "value": 0.74, "series": "debt"}, {"date": "2012-05-01T00:00:00", "value": 0.7440000000000001, "series": "debt"}, {"date": "2012-06-01T00:00:00", "value": 0.753, "series": "debt"}, {"date": "2012-07-01T00:00:00", "value": 0.7509999999999999, "series": "debt"}, {"date": "2012-08-01T00:00:00", "value": 0.75, "series": "debt"}, {"date": "2012-09-01T00:00:00", "value": 0.759, "series": "debt"}, {"date": "2012-10-01T00:00:00", "value": 0.7609999999999999, "series": "debt"}, {"date": "2012-11-01T00:00:00", "value": 0.767, "series": "debt"}, {"date": "2012-12-01T00:00:00", "value": 0.7759999999999999, "series": "debt"}, {"date": "2013-01-01T00:00:00", "value": 0.763, "series": "debt"}, {"date": "2013-02-01T00:00:00", "value": 0.763, "series": "debt"}, {"date": "2013-03-01T00:00:00", "value": 0.775, "series": "debt"}, {"date": "2013-04-01T00:00:00", "value": 0.774, "series": "debt"}, {"date": "2013-05-01T00:00:00", "value": 0.78, "series": "debt"}, {"date": "2013-06-01T00:00:00", "value": 0.785, "series": "debt"}, {"date": "2013-07-01T00:00:00", "value": 0.779, "series": "debt"}, {"date": "2013-08-01T00:00:00", "value": 0.779, "series": "debt"}, {"date": "2013-09-01T00:00:00", "value": 0.785, "series": "debt"}, {"date": "2013-10-01T00:00:00", "value": 0.782, "series": "debt"}, {"date": "2013-11-01T00:00:00", "value": 0.787, "series": "debt"}, {"date": "2013-12-01T00:00:00", "value": 0.7959999999999999, "series": "debt"}, {"date": "2014-01-01T00:00:00", "value": 0.7859999999999999, "series": "debt"}, {"date": "2014-02-01T00:00:00", "value": 0.787, "series": "debt"}, {"date": "2014-03-01T00:00:00", "value": 0.792, "series": "debt"}, {"date": "2014-04-01T00:00:00", "value": 0.7929999999999999, "series": "debt"}, {"date": "2014-05-01T00:00:00", "value": 0.7979999999999999, "series": "debt"}, {"date": "2014-06-01T00:00:00", "value": 0.804, "series": "debt"}, {"date": "2014-07-01T00:00:00", "value": 0.8, "series": "debt"}, {"date": "2014-08-01T00:00:00", "value": 0.8, "series": "debt"}, {"date": "2014-09-01T00:00:00", "value": 0.807, "series": "debt"}, {"date": "2014-10-01T00:00:00", "value": 0.8079999999999999, "series": "debt"}, {"date": "2014-11-01T00:00:00", "value": 0.8109999999999999, "series": "debt"}, {"date": "2014-12-01T00:00:00", "value": 0.821, "series": "debt"}, {"date": "2015-01-01T00:00:00", "value": 0.807, "series": "debt"}, {"date": "2015-02-01T00:00:00", "value": 0.8079999999999999, "series": "debt"}, {"date": "2015-03-01T00:00:00", "value": 0.816, "series": "debt"}, {"date": "2015-04-01T00:00:00", "value": 0.815, "series": "debt"}, {"date": "2015-05-01T00:00:00", "value": 0.821, "series": "debt"}, {"date": "2015-06-01T00:00:00", "value": 0.8270000000000001, "series": "debt"}, {"date": "2015-07-01T00:00:00", "value": 0.8220000000000001, "series": "debt"}, {"date": "2015-08-01T00:00:00", "value": 0.8190000000000001, "series": "debt"}, {"date": "2015-09-01T00:00:00", "value": 0.823, "series": "debt"}, {"date": "2015-10-01T00:00:00", "value": 0.8220000000000001, "series": "debt"}, {"date": "2015-11-01T00:00:00", "value": 0.821, "series": "debt"}, {"date": "2015-12-01T00:00:00", "value": 0.823, "series": "debt"}, {"date": "2016-01-01T00:00:00", "value": 0.81, "series": "debt"}, {"date": "2016-02-01T00:00:00", "value": 0.8059999999999999, "series": "debt"}, {"date": "2016-03-01T00:00:00", "value": 0.813, "series": "debt"}, {"date": "2016-04-01T00:00:00", "value": 0.8140000000000001, "series": "debt"}, {"date": "2016-05-01T00:00:00", "value": 0.815, "series": "debt"}, {"date": "2016-06-01T00:00:00", "value": 0.8170000000000001, "series": "debt"}, {"date": "2016-07-01T00:00:00", "value": 0.8109999999999999, "series": "debt"}, {"date": "2016-08-01T00:00:00", "value": 0.812, "series": "debt"}, {"date": "2016-09-01T00:00:00", "value": 0.8109999999999999, "series": "debt"}, {"date": "2016-10-01T00:00:00", "value": 0.8140000000000001, "series": "debt"}, {"date": "2016-11-01T00:00:00", "value": 0.82, "series": "debt"}, {"date": "2016-12-01T00:00:00", "value": 0.83, "series": "debt"}, {"date": "2017-01-01T00:00:00", "value": 0.812, "series": "debt"}, {"date": "2017-02-01T00:00:00", "value": 0.821, "series": "debt"}, {"date": "2017-03-01T00:00:00", "value": 0.835, "series": "debt"}, {"date": "2017-04-01T00:00:00", "value": 0.8320000000000001, "series": "debt"}, {"date": "2017-05-01T00:00:00", "value": 0.836, "series": "debt"}, {"date": "2017-06-01T00:00:00", "value": 0.843, "series": "debt"}, {"date": "2017-07-01T00:00:00", "value": 0.84, "series": "debt"}, {"date": "2017-08-01T00:00:00", "value": 0.8370000000000001, "series": "debt"}, {"date": "2017-09-01T00:00:00", "value": 0.845, "series": "debt"}, {"date": "2017-10-01T00:00:00", "value": 0.836, "series": "debt"}, {"date": "2017-11-01T00:00:00", "value": 0.828, "series": "debt"}, {"date": "2017-12-01T00:00:00", "value": 0.8240000000000001, "series": "debt"}, {"date": "2018-01-01T00:00:00", "value": 0.815, "series": "debt"}, {"date": "2018-02-01T00:00:00", "value": 0.8220000000000001, "series": "debt"}, {"date": "2018-03-01T00:00:00", "value": 0.823, "series": "debt"}, {"date": "2018-04-01T00:00:00", "value": 0.826, "series": "debt"}, {"date": "2018-05-01T00:00:00", "value": 0.8240000000000001, "series": "debt"}, {"date": "2018-06-01T00:00:00", "value": 0.825, "series": "debt"}, {"date": "2018-07-01T00:00:00", "value": 0.8140000000000001, "series": "debt"}, {"date": "2018-08-01T00:00:00", "value": 0.816, "series": "debt"}, {"date": "2018-09-01T00:00:00", "value": 0.816, "series": "debt"}, {"date": "2018-10-01T00:00:00", "value": 0.815, "series": "debt"}, {"date": "2018-11-01T00:00:00", "value": 0.815, "series": "debt"}, {"date": "2018-12-01T00:00:00", "value": 0.818, "series": "debt"}, {"date": "2019-01-01T00:00:00", "value": 0.804, "series": "debt"}, {"date": "2019-02-01T00:00:00", "value": 0.8029999999999999, "series": "debt"}, {"date": "2019-03-01T00:00:00", "value": 0.8029999999999999, "series": "debt"}, {"date": "2019-04-01T00:00:00", "value": 0.805, "series": "debt"}, {"date": "2019-05-01T00:00:00", "value": 0.8079999999999999, "series": "debt"}, {"date": "2019-06-01T00:00:00", "value": 0.81, "series": "debt"}, {"date": "2019-07-01T00:00:00", "value": 0.8029999999999999, "series": "debt"}, {"date": "2019-08-01T00:00:00", "value": 0.799, "series": "debt"}, {"date": "2019-09-01T00:00:00", "value": 0.804, "series": "debt"}, {"date": "2019-10-01T00:00:00", "value": 0.821, "series": "debt"}, {"date": "2019-11-01T00:00:00", "value": 0.8340000000000001, "series": "debt"}, {"date": "2019-12-01T00:00:00", "value": 0.848, "series": "debt"}, {"date": "2020-01-01T00:00:00", "value": 0.8420000000000001, "series": "debt"}, {"date": "2020-02-01T00:00:00", "value": 0.845, "series": "debt"}, {"date": "2020-03-01T00:00:00", "value": 0.852, "series": "debt"}, {"date": "2020-04-01T00:00:00", "value": 0.904, "series": "debt"}, {"date": "2020-05-01T00:00:00", "value": 0.941, "series": "debt"}, {"date": "2020-06-01T00:00:00", "value": 0.9620000000000001, "series": "debt"}, {"date": "2020-07-01T00:00:00", "value": 0.97, "series": "debt"}, {"date": "2020-08-01T00:00:00", "value": 0.988, "series": "debt"}, {"date": "2020-09-01T00:00:00", "value": 0.992, "series": "debt"}, {"date": "2020-10-01T00:00:00", "value": 0.992, "series": "debt"}, {"date": "2020-11-01T00:00:00", "value": 0.991, "series": "debt"}, {"date": "2020-12-01T00:00:00", "value": 0.987, "series": "debt"}, {"date": "2021-01-01T00:00:00", "value": 0.971, "series": "debt"}, {"date": "2021-02-01T00:00:00", "value": 0.9740000000000001, "series": "debt"}, {"date": "2021-03-01T00:00:00", "value": 0.965, "series": "debt"}, {"date": "2021-04-01T00:00:00", "value": 0.9740000000000001, "series": "debt"}, {"date": "2021-05-01T00:00:00", "value": 0.9790000000000001, "series": "debt"}, {"date": "2021-06-01T00:00:00", "value": 0.9740000000000001, "series": "debt"}, {"date": "2021-07-01T00:00:00", "value": 0.968, "series": "debt"}, {"date": "2021-08-01T00:00:00", "value": 0.9520000000000001, "series": "debt"}, {"date": "2021-09-01T00:00:00", "value": 0.9470000000000001, "series": "debt"}, {"date": "2021-10-01T00:00:00", "value": 0.975, "series": "debt"}, {"date": "2021-11-01T00:00:00", "value": 0.981, "series": "debt"}, {"date": "2021-12-01T00:00:00", "value": 0.9790000000000001, "series": "debt"}, {"date": "2022-01-01T00:00:00", "value": 0.9670000000000001, "series": "debt"}, {"date": "2022-02-01T00:00:00", "value": 0.96, "series": "debt"}, {"date": "2022-03-01T00:00:00", "value": 0.966, "series": "debt"}, {"date": "2022-04-01T00:00:00", "value": 0.9620000000000001, "series": "debt"}, {"date": "2022-05-01T00:00:00", "value": 0.9640000000000001, "series": "debt"}, {"date": "2022-06-01T00:00:00", "value": 0.9670000000000001, "series": "debt"}, {"date": "2022-07-01T00:00:00", "value": 0.9590000000000001, "series": "debt"}, {"date": "2022-08-01T00:00:00", "value": 0.958, "series": "debt"}, {"date": "2022-09-01T00:00:00", "value": 0.956, "series": "debt"}, {"date": "2022-10-01T00:00:00", "value": 0.9540000000000001, "series": "debt"}, {"date": "2022-11-01T00:00:00", "value": 0.956, "series": "debt"}, {"date": "2022-12-01T00:00:00", "value": 0.958, "series": "debt"}, {"date": "2023-01-01T00:00:00", "value": 0.948, "series": "debt"}, {"date": "2023-02-01T00:00:00", "value": 0.948, "series": "debt"}, {"date": "2023-03-01T00:00:00", "value": 0.9570000000000001, "series": "debt"}, {"date": "2023-04-01T00:00:00", "value": 0.9540000000000001, "series": "debt"}, {"date": "2023-05-01T00:00:00", "value": 0.961, "series": "debt"}, {"date": "2023-06-01T00:00:00", "value": 0.9670000000000001, "series": "debt"}, {"date": "2023-07-01T00:00:00", "value": 0.9570000000000001, "series": "debt"}, {"date": "2023-08-01T00:00:00", "value": 0.958, "series": "debt"}, {"date": "2023-09-01T00:00:00", "value": 0.956, "series": "debt"}, {"date": "2023-10-01T00:00:00", "value": 0.971, "series": "debt"}, {"date": "2023-11-01T00:00:00", "value": 0.98, "series": "debt"}, {"date": "2023-12-01T00:00:00", "value": 0.9840000000000001, "series": "debt"}, {"date": "2024-01-01T00:00:00", "value": 0.968, "series": "debt"}, {"date": "2024-02-01T00:00:00", "value": 0.9740000000000001, "series": "debt"}, {"date": "2024-03-01T00:00:00", "value": 0.983, "series": "debt"}, {"date": "2024-04-01T00:00:00", "value": 0.9790000000000001, "series": "debt"}], "data-f2d687ca02b6c70826dbff1fc4d1c1d4": [{"date": "1992-01-01T00:00:00", "value": 0.035}, {"date": "1992-04-01T00:00:00", "value": 0.077}, {"date": "1992-07-01T00:00:00", "value": 0.06}, {"date": "1992-10-01T00:00:00", "value": 0.051}, {"date": "1993-01-01T00:00:00", "value": 0.068}, {"date": "1993-04-01T00:00:00", "value": 0.085}, {"date": "1993-07-01T00:00:00", "value": 0.064}, {"date": "1993-10-01T00:00:00", "value": 0.055}, {"date": "1994-01-01T00:00:00", "value": 0.066}, {"date": "1994-04-01T00:00:00", "value": 0.075}, {"date": "1994-07-01T00:00:00", "value": 0.055}, {"date": "1994-10-01T00:00:00", "value": 0.04}, {"date": "1995-01-01T00:00:00", "value": 0.059000000000000004}, {"date": "1995-04-01T00:00:00", "value": 0.061}, {"date": "1995-07-01T00:00:00", "value": 0.055999999999999994}, {"date": "1995-10-01T00:00:00", "value": 0.032}, {"date": "1996-01-01T00:00:00", "value": 0.034}, {"date": "1996-04-01T00:00:00", "value": 0.071}, {"date": "1996-07-01T00:00:00", "value": 0.04}, {"date": "1996-10-01T00:00:00", "value": 0.008}, {"date": "1997-01-01T00:00:00", "value": 0.023}, {"date": "1997-04-01T00:00:00", "value": 0.049}, {"date": "1997-07-01T00:00:00", "value": 0.026000000000000002}, {"date": "1997-10-01T00:00:00", "value": -0.008}, {"date": "1998-01-01T00:00:00", "value": -0.017}, {"date": "1998-04-01T00:00:00", "value": 0.04}, {"date": "1998-07-01T00:00:00", "value": 0.005}, {"date": "1998-10-01T00:00:00", "value": -0.01}, {"date": "1999-01-01T00:00:00", "value": -0.03}, {"date": "1999-04-01T00:00:00", "value": 0.026000000000000002}, {"date": "1999-07-01T00:00:00", "value": -0.006}, {"date": "1999-10-01T00:00:00", "value": -0.015}, {"date": "2000-01-01T00:00:00", "value": -0.042}, {"date": "2000-04-01T00:00:00", "value": -0.012}, {"date": "2000-07-01T00:00:00", "value": -0.015}, {"date": "2000-10-01T00:00:00", "value": 0.013999999999999999}, {"date": "2001-01-01T00:00:00", "value": -0.042}, {"date": "2001-04-01T00:00:00", "value": 0.002}, {"date": "2001-07-01T00:00:00", "value": -0.006}, {"date": "2001-10-01T00:00:00", "value": 0.032}, {"date": "2002-01-01T00:00:00", "value": -0.01}, {"date": "2002-04-01T00:00:00", "value": 0.03}, {"date": "2002-07-01T00:00:00", "value": 0.018000000000000002}, {"date": "2002-10-01T00:00:00", "value": 0.04}, {"date": "2003-01-01T00:00:00", "value": 0.013999999999999999}, {"date": "2003-04-01T00:00:00", "value": 0.04}, {"date": "2003-07-01T00:00:00", "value": 0.033}, {"date": "2003-10-01T00:00:00", "value": 0.042}, {"date": "2004-01-01T00:00:00", "value": 0.004}, {"date": "2004-04-01T00:00:00", "value": 0.045}, {"date": "2004-07-01T00:00:00", "value": 0.034}, {"date": "2004-10-01T00:00:00", "value": 0.043}, {"date": "2005-01-01T00:00:00", "value": 0.012}, {"date": "2005-04-01T00:00:00", "value": 0.037000000000000005}, {"date": "2005-07-01T00:00:00", "value": 0.027999999999999997}, {"date": "2005-10-01T00:00:00", "value": 0.049}, {"date": "2006-01-01T00:00:00", "value": 0.006999999999999999}, {"date": "2006-04-01T00:00:00", "value": 0.034}, {"date": "2006-07-01T00:00:00", "value": 0.028999999999999998}, {"date": "2006-10-01T00:00:00", "value": 0.040999999999999995}, {"date": "2007-01-01T00:00:00", "value": 0.001}, {"date": "2007-04-01T00:00:00", "value": 0.032}, {"date": "2007-07-01T00:00:00", "value": 0.028999999999999998}, {"date": "2007-10-01T00:00:00", "value": 0.044000000000000004}, {"date": "2008-01-01T00:00:00", "value": 0.012}, {"date": "2008-04-01T00:00:00", "value": 0.05}, {"date": "2008-07-01T00:00:00", "value": 0.055}, {"date": "2008-10-01T00:00:00", "value": 0.08900000000000001}, {"date": "2009-01-01T00:00:00", "value": 0.08}, {"date": "2009-04-01T00:00:00", "value": 0.10300000000000001}, {"date": "2009-07-01T00:00:00", "value": 0.09300000000000001}, {"date": "2009-10-01T00:00:00", "value": 0.126}, {"date": "2010-01-01T00:00:00", "value": 0.08}, {"date": "2010-04-01T00:00:00", "value": 0.087}, {"date": "2010-07-01T00:00:00", "value": 0.09}, {"date": "2010-10-01T00:00:00", "value": 0.11199999999999999}, {"date": "2011-01-01T00:00:00", "value": 0.062}, {"date": "2011-04-01T00:00:00", "value": 0.078}, {"date": "2011-07-01T00:00:00", "value": 0.067}, {"date": "2011-10-01T00:00:00", "value": 0.08900000000000001}, {"date": "2012-01-01T00:00:00", "value": 0.061}, {"date": "2012-04-01T00:00:00", "value": 0.102}, {"date": "2012-07-01T00:00:00", "value": 0.065}, {"date": "2012-10-01T00:00:00", "value": 0.092}, {"date": "2013-01-01T00:00:00", "value": 0.031}, {"date": "2013-04-01T00:00:00", "value": 0.045}, {"date": "2013-07-01T00:00:00", "value": 0.059000000000000004}, {"date": "2013-10-01T00:00:00", "value": 0.079}, {"date": "2014-01-01T00:00:00", "value": 0.040999999999999995}, {"date": "2014-04-01T00:00:00", "value": 0.062}, {"date": "2014-07-01T00:00:00", "value": 0.055999999999999994}, {"date": "2014-10-01T00:00:00", "value": 0.063}, {"date": "2015-01-01T00:00:00", "value": 0.021}, {"date": "2015-04-01T00:00:00", "value": 0.055999999999999994}, {"date": "2015-07-01T00:00:00", "value": 0.051}, {"date": "2015-10-01T00:00:00", "value": 0.055999999999999994}, {"date": "2016-01-01T00:00:00", "value": 0.011000000000000001}, {"date": "2016-04-01T00:00:00", "value": 0.045}, {"date": "2016-07-01T00:00:00", "value": 0.039}, {"date": "2016-10-01T00:00:00", "value": 0.037000000000000005}, {"date": "2017-01-01T00:00:00", "value": -0.012}, {"date": "2017-04-01T00:00:00", "value": 0.047}, {"date": "2017-07-01T00:00:00", "value": 0.033}, {"date": "2017-10-01T00:00:00", "value": 0.032}, {"date": "2018-01-01T00:00:00", "value": 0.003}, {"date": "2018-04-01T00:00:00", "value": 0.032}, {"date": "2018-07-01T00:00:00", "value": 0.023}, {"date": "2018-10-01T00:00:00", "value": 0.033}, {"date": "2019-01-01T00:00:00", "value": -0.013000000000000001}, {"date": "2019-04-01T00:00:00", "value": 0.042}, {"date": "2019-07-01T00:00:00", "value": 0.028999999999999998}, {"date": "2019-10-01T00:00:00", "value": 0.040999999999999995}, {"date": "2020-01-01T00:00:00", "value": 0.006}, {"date": "2020-04-01T00:00:00", "value": 0.281}, {"date": "2020-07-01T00:00:00", "value": 0.147}, {"date": "2020-10-01T00:00:00", "value": 0.115}, {"date": "2021-01-01T00:00:00", "value": 0.086}, {"date": "2021-04-01T00:00:00", "value": 0.11699999999999999}, {"date": "2021-07-01T00:00:00", "value": 0.07}, {"date": "2021-10-01T00:00:00", "value": 0.045}, {"date": "2022-01-01T00:00:00", "value": 0.011000000000000001}, {"date": "2022-04-01T00:00:00", "value": 0.07}, {"date": "2022-07-01T00:00:00", "value": 0.043}, {"date": "2022-10-01T00:00:00", "value": 0.065}, {"date": "2023-01-01T00:00:00", "value": 0.037000000000000005}, {"date": "2023-04-01T00:00:00", "value": 0.085}, {"date": "2023-07-01T00:00:00", "value": 0.052000000000000005}, {"date": "2023-10-01T00:00:00", "value": 0.06}]}}