{"config": {"font": "Circular Std", "text": {"color": "#676A86", "align": "left", "baseline": "middle", "dx": 7, "dy": 0, "fontSize": 11}, "view": {"stroke": null, "continuousWidth": 400, "continuousHeight": 300, "discreteWidth": 400, "discreteHeight": 300}, "range": {"category": ["#36B7B4", "#E6224B", "#F4C245", "#0063AF", "#00A767", "#179FDB", "#EB5C2E"], "diverging": ["#E6224B", "#E54753", "#C9C9C9", "#179FDB", "#122B39"], "heatmap": ["#C9C9C9", "#179FDB", "#0063AF", "#122B39"], "ordinal": ["#00A767", "#36B7B4", "#179FDB", "#0063AF", "#243B5A"]}, "bar": {"color": "#179fdb"}, "line": {"color": "#e6224b"}, "rule": {"color": "#676A86"}, "area": {"opacity": 0.3}, "point": {"filled": true, "size": 80, "color": "#e6224b", "opacity": 0.95}, "geoshape": {"stroke": "white", "strokeWidth": 0.3}, "rect": {"fill": "#d6d4d4", "opacity": 0.3}, "axis": {"labelColor": "#676A86", "labelFontSize": 11, "labelFont": "Circular Std", "labelOpacity": 0.7, "tickColor": "#676A86", "tickOpacity": 0.5, "domainColor": "#676A86", "domainOpacity": 0.5, "gridColor": "#676A86", "gridDash": [2, 2], "gridOpacity": 0.5, "title": null, "titleColor": "#676A86", "titleOpacity": 0.8, "tickSize": 4}, "axisXDiscrete": {"grid": false, "labelAngle": 0, "tickCount": 10, "tickOpacity": 0.5, "title": null}, "axisYDiscrete": {"ticks": false, "labelPadding": 5}, "axisXTemporal": {"grid": false, "ticks": true}, "axisXQuantitative": {"grid": true}, "axisYQuantitative": {"gridColor": "#676A86", "gridDash": [1, 5], "gridOpacity": 0.5, "ticks": false, "labelPadding": 5, "tickCount": 8, "titleAngle": 0, "titleAlign": "left", "titleBaseline": "bottom", "titleX": 0, "titleY": -5}, "title": {"color": "#676A86E6", "subtitleColor": "#676A86", "font": "Circular Std", "subtitleFont": "Circular Std", "anchor": "start", "fontSize": 14, "subtitleFontSize": 12, "subtitlePadding": 4, "offset": 0, "frame": "group"}, "legend": {"titleColor": "#122b39", "title": null, "labelColor": "#122b39", "labelFontSize": 11}}, "layer": [{"data": {"name": "data-a0a55d106695e8d630baff0f16eee66d"}, "mark": {"type": "rule", "color": "lightgrey", "strokeWidth": 2}, "encoding": {"y": {"field": "y", "type": "quantitative"}}}, {"data": {"name": "data-5a7ae036b28af15651e0fe90ccb64c9b"}, "mark": {"type": "line"}, "encoding": {"color": {"value": "#2a9d8f"}, "tooltip": [{"field": "Year", "format": "%Y", "title": "Year", "type": "temporal"}, {"field": "VALUE_label", "title": "Net Migration", "type": "nominal"}], "x": {"axis": {"labelFontSize": 14}, "field": "Year", "type": "temporal"}, "y": {"axis": {"labelExpr": "datum.value + 'K'", "labelFontSize": 14}, "field": "VALUE", "scale": {"domain": [-100, 120]}, "type": "quantitative"}}}], "height": 400, "width": 600, "$schema": "https://vega.github.io/schema/vega-lite/v5.20.1.json", "datasets": {"data-a0a55d106695e8d630baff0f16eee66d": [{"y": 0}], "data-5a7ae036b28af15651e0fe90ccb64c9b": [{"STATISTIC Label": "Annual Population Change", "Year": "1951-01-01T00:00:00", "Component": "Net migration", "UNIT": "Thousand", "VALUE": -35.0, "VALUE_label": "-35.0K"}, {"STATISTIC Label": "Annual Population Change", "Year": "1952-01-01T00:00:00", "Component": "Net migration", "UNIT": "Thousand", "VALUE": -35.0, "VALUE_label": "-35.0K"}, {"STATISTIC Label": "Annual Population Change", "Year": "1953-01-01T00:00:00", "Component": "Net migration", "UNIT": "Thousand", "VALUE": -33.0, "VALUE_label": "-33.0K"}, {"STATISTIC Label": "Annual Population Change", "Year": "1954-01-01T00:00:00", "Component": "Net migration", "UNIT": "Thousand", "VALUE": -36.0, "VALUE_label": "-36.0K"}, {"STATISTIC Label": "Annual Population Change", "Year": "1955-01-01T00:00:00", "Component": "Net migration", "UNIT": "Thousand", "VALUE": -45.0, "VALUE_label": "-45.0K"}, {"STATISTIC Label": "Annual Population Change", "Year": "1956-01-01T00:00:00", "Component": "Net migration", "UNIT": "Thousand", "VALUE": -48.0, "VALUE_label": "-48.0K"}, {"STATISTIC Label": "Annual Population Change", "Year": "1957-01-01T00:00:00", "Component": "Net migration", "UNIT": "Thousand", "VALUE": -41.0, "VALUE_label": "-41.0K"}, {"STATISTIC Label": "Annual Population Change", "Year": "1958-01-01T00:00:00", "Component": "Net migration", "UNIT": "Thousand", "VALUE": -58.0, "VALUE_label": "-58.0K"}, {"STATISTIC Label": "Annual Population Change", "Year": "1959-01-01T00:00:00", "Component": "Net migration", "UNIT": "Thousand", "VALUE": -32.0, "VALUE_label": "-32.0K"}, {"STATISTIC Label": "Annual Population Change", "Year": "1960-01-01T00:00:00", "Component": "Net migration", "UNIT": "Thousand", "VALUE": -41.0, "VALUE_label": "-41.0K"}, {"STATISTIC Label": "Annual Population Change", "Year": "1961-01-01T00:00:00", "Component": "Net migration", "UNIT": "Thousand", "VALUE": -40.0, "VALUE_label": "-40.0K"}, {"STATISTIC Label": "Annual Population Change", "Year": "1962-01-01T00:00:00", "Component": "Net migration", "UNIT": "Thousand", "VALUE": -15.0, "VALUE_label": "-15.0K"}, {"STATISTIC Label": "Annual Population Change", "Year": "1963-01-01T00:00:00", "Component": "Net migration", "UNIT": "Thousand", "VALUE": -8.0, "VALUE_label": "-8.0K"}, {"STATISTIC Label": "Annual Population Change", "Year": "1964-01-01T00:00:00", "Component": "Net migration", "UNIT": "Thousand", "VALUE": -17.0, "VALUE_label": "-17.0K"}, {"STATISTIC Label": "Annual Population Change", "Year": "1965-01-01T00:00:00", "Component": "Net migration", "UNIT": "Thousand", "VALUE": -20.0, "VALUE_label": "-20.0K"}, {"STATISTIC Label": "Annual Population Change", "Year": "1966-01-01T00:00:00", "Component": "Net migration", "UNIT": "Thousand", "VALUE": -21.0, "VALUE_label": "-21.0K"}, {"STATISTIC Label": "Annual Population Change", "Year": "1967-01-01T00:00:00", "Component": "Net migration", "UNIT": "Thousand", "VALUE": -13.0, "VALUE_label": "-13.0K"}, {"STATISTIC Label": "Annual Population Change", "Year": "1968-01-01T00:00:00", "Component": "Net migration", "UNIT": "Thousand", "VALUE": -16.0, "VALUE_label": "-16.0K"}, {"STATISTIC Label": "Annual Population Change", "Year": "1969-01-01T00:00:00", "Component": "Net migration", "UNIT": "Thousand", "VALUE": -15.0, "VALUE_label": "-15.0K"}, {"STATISTIC Label": "Annual Population Change", "Year": "1970-01-01T00:00:00", "Component": "Net migration", "UNIT": "Thousand", "VALUE": -5.0, "VALUE_label": "-5.0K"}, {"STATISTIC Label": "Annual Population Change", "Year": "1971-01-01T00:00:00", "Component": "Net migration", "UNIT": "Thousand", "VALUE": -5.0, "VALUE_label": "-5.0K"}, {"STATISTIC Label": "Annual Population Change", "Year": "1972-01-01T00:00:00", "Component": "Net migration", "UNIT": "Thousand", "VALUE": 11.0, "VALUE_label": "11.0K"}, {"STATISTIC Label": "Annual Population Change", "Year": "1973-01-01T00:00:00", "Component": "Net migration", "UNIT": "Thousand", "VALUE": 13.0, "VALUE_label": "13.0K"}, {"STATISTIC Label": "Annual Population Change", "Year": "1974-01-01T00:00:00", "Component": "Net migration", "UNIT": "Thousand", "VALUE": 16.0, "VALUE_label": "16.0K"}, {"STATISTIC Label": "Annual Population Change", "Year": "1975-01-01T00:00:00", "Component": "Net migration", "UNIT": "Thousand", "VALUE": 20.0, "VALUE_label": "20.0K"}, {"STATISTIC Label": "Annual Population Change", "Year": "1976-01-01T00:00:00", "Component": "Net migration", "UNIT": "Thousand", "VALUE": 16.0, "VALUE_label": "16.0K"}, {"STATISTIC Label": "Annual Population Change", "Year": "1977-01-01T00:00:00", "Component": "Net migration", "UNIT": "Thousand", "VALUE": 10.0, "VALUE_label": "10.0K"}, {"STATISTIC Label": "Annual Population Change", "Year": "1978-01-01T00:00:00", "Component": "Net migration", "UNIT": "Thousand", "VALUE": 7.0, "VALUE_label": "7.0K"}, {"STATISTIC Label": "Annual Population Change", "Year": "1979-01-01T00:00:00", "Component": "Net migration", "UNIT": "Thousand", "VALUE": 16.0, "VALUE_label": "16.0K"}, {"STATISTIC Label": "Annual Population Change", "Year": "1980-01-01T00:00:00", "Component": "Net migration", "UNIT": "Thousand", "VALUE": -8.0, "VALUE_label": "-8.0K"}, {"STATISTIC Label": "Annual Population Change", "Year": "1981-01-01T00:00:00", "Component": "Net migration", "UNIT": "Thousand", "VALUE": 2.0, "VALUE_label": "2.0K"}, {"STATISTIC Label": "Annual Population Change", "Year": "1982-01-01T00:00:00", "Component": "Net migration", "UNIT": "Thousand", "VALUE": -1.0, "VALUE_label": "-1.0K"}, {"STATISTIC Label": "Annual Population Change", "Year": "1983-01-01T00:00:00", "Component": "Net migration", "UNIT": "Thousand", "VALUE": -14.0, "VALUE_label": "-14.0K"}, {"STATISTIC Label": "Annual Population Change", "Year": "1984-01-01T00:00:00", "Component": "Net migration", "UNIT": "Thousand", "VALUE": -9.0, "VALUE_label": "-9.0K"}, {"STATISTIC Label": "Annual Population Change", "Year": "1985-01-01T00:00:00", "Component": "Net migration", "UNIT": "Thousand", "VALUE": -20.0, "VALUE_label": "-20.0K"}, {"STATISTIC Label": "Annual Population Change", "Year": "1986-01-01T00:00:00", "Component": "Net migration", "UNIT": "Thousand", "VALUE": -28.0, "VALUE_label": "-28.0K"}, {"STATISTIC Label": "Annual Population Change", "Year": "1987-01-01T00:00:00", "Component": "Net migration", "UNIT": "Thousand", "VALUE": -23.0, "VALUE_label": "-23.0K"}, {"STATISTIC Label": "Annual Population Change", "Year": "1988-01-01T00:00:00", "Component": "Net migration", "UNIT": "Thousand", "VALUE": -41.9, "VALUE_label": "-41.9K"}, {"STATISTIC Label": "Annual Population Change", "Year": "1989-01-01T00:00:00", "Component": "Net migration", "UNIT": "Thousand", "VALUE": -43.9, "VALUE_label": "-43.9K"}, {"STATISTIC Label": "Annual Population Change", "Year": "1990-01-01T00:00:00", "Component": "Net migration", "UNIT": "Thousand", "VALUE": -22.9, "VALUE_label": "-22.9K"}, {"STATISTIC Label": "Annual Population Change", "Year": "1991-01-01T00:00:00", "Component": "Net migration", "UNIT": "Thousand", "VALUE": -2.0, "VALUE_label": "-2.0K"}, {"STATISTIC Label": "Annual Population Change", "Year": "1992-01-01T00:00:00", "Component": "Net migration", "UNIT": "Thousand", "VALUE": 7.4, "VALUE_label": "7.4K"}, {"STATISTIC Label": "Annual Population Change", "Year": "1993-01-01T00:00:00", "Component": "Net migration", "UNIT": "Thousand", "VALUE": -0.4, "VALUE_label": "-0.4K"}, {"STATISTIC Label": "Annual Population Change", "Year": "1994-01-01T00:00:00", "Component": "Net migration", "UNIT": "Thousand", "VALUE": -4.7, "VALUE_label": "-4.7K"}, {"STATISTIC Label": "Annual Population Change", "Year": "1995-01-01T00:00:00", "Component": "Net migration", "UNIT": "Thousand", "VALUE": -1.9, "VALUE_label": "-1.9K"}, {"STATISTIC Label": "Annual Population Change", "Year": "1996-01-01T00:00:00", "Component": "Net migration", "UNIT": "Thousand", "VALUE": 8.0, "VALUE_label": "8.0K"}, {"STATISTIC Label": "Annual Population Change", "Year": "1997-01-01T00:00:00", "Component": "Net migration", "UNIT": "Thousand", "VALUE": 19.2, "VALUE_label": "19.2K"}, {"STATISTIC Label": "Annual Population Change", "Year": "1998-01-01T00:00:00", "Component": "Net migration", "UNIT": "Thousand", "VALUE": 17.4, "VALUE_label": "17.4K"}, {"STATISTIC Label": "Annual Population Change", "Year": "1999-01-01T00:00:00", "Component": "Net migration", "UNIT": "Thousand", "VALUE": 17.3, "VALUE_label": "17.3K"}, {"STATISTIC Label": "Annual Population Change", "Year": "2000-01-01T00:00:00", "Component": "Net migration", "UNIT": "Thousand", "VALUE": 26.0, "VALUE_label": "26.0K"}, {"STATISTIC Label": "Annual Population Change", "Year": "2001-01-01T00:00:00", "Component": "Net migration", "UNIT": "Thousand", "VALUE": 32.8, "VALUE_label": "32.8K"}, {"STATISTIC Label": "Annual Population Change", "Year": "2002-01-01T00:00:00", "Component": "Net migration", "UNIT": "Thousand", "VALUE": 41.3, "VALUE_label": "41.3K"}, {"STATISTIC Label": "Annual Population Change", "Year": "2003-01-01T00:00:00", "Component": "Net migration", "UNIT": "Thousand", "VALUE": 30.7, "VALUE_label": "30.7K"}, {"STATISTIC Label": "Annual Population Change", "Year": "2004-01-01T00:00:00", "Component": "Net migration", "UNIT": "Thousand", "VALUE": 32.0, "VALUE_label": "32.0K"}, {"STATISTIC Label": "Annual Population Change", "Year": "2005-01-01T00:00:00", "Component": "Net migration", "UNIT": "Thousand", "VALUE": 55.1, "VALUE_label": "55.1K"}, {"STATISTIC Label": "Annual Population Change", "Year": "2006-01-01T00:00:00", "Component": "Net migration", "UNIT": "Thousand", "VALUE": 71.8, "VALUE_label": "71.8K"}, {"STATISTIC Label": "Annual Population Change", "Year": "2007-01-01T00:00:00", "Component": "Net migration", "UNIT": "Thousand", "VALUE": 104.8, "VALUE_label": "104.8K"}, {"STATISTIC Label": "Annual Population Change", "Year": "2008-01-01T00:00:00", "Component": "Net migration", "UNIT": "Thousand", "VALUE": 64.3, "VALUE_label": "64.3K"}, {"STATISTIC Label": "Annual Population Change", "Year": "2009-01-01T00:00:00", "Component": "Net migration", "UNIT": "Thousand", "VALUE": 1.6, "VALUE_label": "1.6K"}, {"STATISTIC Label": "Annual Population Change", "Year": "2010-01-01T00:00:00", "Component": "Net migration", "UNIT": "Thousand", "VALUE": -27.5, "VALUE_label": "-27.5K"}, {"STATISTIC Label": "Annual Population Change", "Year": "2011-01-01T00:00:00", "Component": "Net migration", "UNIT": "Thousand", "VALUE": -27.4, "VALUE_label": "-27.4K"}, {"STATISTIC Label": "Annual Population Change", "Year": "2012-01-01T00:00:00", "Component": "Net migration", "UNIT": "Thousand", "VALUE": -25.7, "VALUE_label": "-25.7K"}, {"STATISTIC Label": "Annual Population Change", "Year": "2013-01-01T00:00:00", "Component": "Net migration", "UNIT": "Thousand", "VALUE": -18.7, "VALUE_label": "-18.7K"}, {"STATISTIC Label": "Annual Population Change", "Year": "2014-01-01T00:00:00", "Component": "Net migration", "UNIT": "Thousand", "VALUE": -8.5, "VALUE_label": "-8.5K"}, {"STATISTIC Label": "Annual Population Change", "Year": "2015-01-01T00:00:00", "Component": "Net migration", "UNIT": "Thousand", "VALUE": 5.9, "VALUE_label": "5.9K"}, {"STATISTIC Label": "Annual Population Change", "Year": "2016-01-01T00:00:00", "Component": "Net migration", "UNIT": "Thousand", "VALUE": 16.2, "VALUE_label": "16.2K"}, {"STATISTIC Label": "Annual Population Change", "Year": "2017-01-01T00:00:00", "Component": "Net migration", "UNIT": "Thousand", "VALUE": 39.2, "VALUE_label": "39.2K"}, {"STATISTIC Label": "Annual Population Change", "Year": "2018-01-01T00:00:00", "Component": "Net migration", "UNIT": "Thousand", "VALUE": 44.4, "VALUE_label": "44.4K"}, {"STATISTIC Label": "Annual Population Change", "Year": "2019-01-01T00:00:00", "Component": "Net migration", "UNIT": "Thousand", "VALUE": 44.0, "VALUE_label": "44.0K"}, {"STATISTIC Label": "Annual Population Change", "Year": "2020-01-01T00:00:00", "Component": "Net migration", "UNIT": "Thousand", "VALUE": 44.7, "VALUE_label": "44.7K"}, {"STATISTIC Label": "Annual Population Change", "Year": "2021-01-01T00:00:00", "Component": "Net migration", "UNIT": "Thousand", "VALUE": 21.8, "VALUE_label": "21.8K"}, {"STATISTIC Label": "Annual Population Change", "Year": "2022-01-01T00:00:00", "Component": "Net migration", "UNIT": "Thousand", "VALUE": 51.7, "VALUE_label": "51.7K"}, {"STATISTIC Label": "Annual Population Change", "Year": "2023-01-01T00:00:00", "Component": "Net migration", "UNIT": "Thousand", "VALUE": 77.6, "VALUE_label": "77.6K"}, {"STATISTIC Label": "Annual Population Change", "Year": "2024-01-01T00:00:00", "Component": "Net migration", "UNIT": "Thousand", "VALUE": 79.3, "VALUE_label": "79.3K"}, {"STATISTIC Label": "Annual Population Change", "Year": "2025-01-01T00:00:00", "Component": "Net migration", "UNIT": "Thousand", "VALUE": 59.7, "VALUE_label": "59.7K"}]}}